{
  "segments": [
    {
      "start": 0.0,
      "end": 5.8,
      "speaker": "SPEAKER_00",
      "text": "Ayer se completó el primero de los cuatro parones de selecciones de esta temporada,"
    },
    {
      "start": 5.8,
      "end": 10.84,
      "speaker": "SPEAKER_00",
      "text": "que debe llevarnos evidentemente a una Copa del Mundo que arranca en nueve meses."
    },
    {
      "start": 10.84,
      "end": 16.12,
      "speaker": "SPEAKER_00",
      "text": "Queda bastante todavía, pero ya estamos en temporada de Mundial y sabemos lo que condiciona"
    },
    {
      "start": 16.12,
      "end": 19.56,
      "speaker": "SPEAKER_00",
      "text": "eso a futbolistas, entrenadores, equipos, etc."
    },
    {
      "start": 19.56,
      "end": 24.76,
      "speaker": "SPEAKER_00",
      "text": "Es el momento perfecto para inaugurar una nueva sección aquí en la pizarra de Quintana,"
    },
    {
      "start": 24.76,
      "end": 29.92,
      "speaker": "SPEAKER_00",
      "text": "el Power Ranking del Mundial 2026, con el que vamos a ordenar parón a parón a nuestras"
    },
    {
      "start": 29.92,
      "end": 33.88,
      "speaker": "SPEAKER_00",
      "text": "diez grandes favoritas de cara al Mundial."
    },
    {
      "start": 33.88,
      "end": 38.6,
      "speaker": "SPEAKER_00",
      "text": "Ya hacemos en nuestro canal de YouTube, en Pizarritas, un Power Ranking del Fútbol Europeo."
    },
    {
      "start": 38.6,
      "end": 42.2,
      "speaker": "SPEAKER_00",
      "text": "Aquí medimos resultados, por supuesto, pero vamos un poquito más allá."
    },
    {
      "start": 42.2,
      "end": 47.28,
      "speaker": "SPEAKER_00",
      "text": "Niveles, sensaciones de cara al Mundial, a sabiendas de que todavía hay muchas selecciones"
    },
    {
      "start": 47.28,
      "end": 48.8,
      "speaker": "SPEAKER_00",
      "text": "que no están clasificadas."
    },
    {
      "start": 48.8,
      "end": 51.08,
      "speaker": "SPEAKER_00",
      "text": "Pero bueno, vamos haciendo ya nuestra quiniela."
    },
    {
      "start": 51.08,
      "end": 54.8,
      "speaker": "SPEAKER_01",
      "text": "Sí, y quizá este primero tenga alguna sorpresita."
    },
    {
      "start": 54.8,
      "end": 55.8,
      "speaker": "SPEAKER_01",
      "text": "¿Tú crees?"
    },
    {
      "start": 55.8,
      "end": 58.76,
      "speaker": "SPEAKER_02",
      "text": "No sé, yo creo que hay alguna selección ahora que la gente igual no espera."
    },
    {
      "start": 58.76,
      "end": 63.56,
      "speaker": "SPEAKER_02",
      "text": "A mí hay una selección que creo que está baja, que la vi ayer, llevaba tiempo sin verla"
    },
    {
      "start": 63.56,
      "end": 64.56,
      "speaker": "SPEAKER_02",
      "text": "y me gustó."
    },
    {
      "start": 64.56,
      "end": 67.24,
      "speaker": "SPEAKER_00",
      "text": "Yo estoy contento con el top 10 que nos ha salido."
    },
    {
      "start": 67.24,
      "end": 69.48,
      "speaker": "SPEAKER_00",
      "text": "Yo creo que hay una selección que no debería estar."
    },
    {
      "start": 69.48,
      "end": 70.48,
      "speaker": "SPEAKER_00",
      "text": "Vale."
    },
    {
      "start": 70.48,
      "end": 74.28,
      "speaker": "SPEAKER_00",
      "text": "Vamos ya con el ranking porque estamos sin mucho tiempo, no nos vamos a meter a la sección"
    },
    {
      "start": 74.28,
      "end": 78.8,
      "speaker": "SPEAKER_00",
      "text": "clasificada, ya le iremos comentando y ya lo iremos actualizando parón a parón."
    },
    {
      "start": 78.8,
      "end": 83.75999999999999,
      "speaker": "SPEAKER_00",
      "text": "No estaba lo de Cabo Verde tampoco en la escaleta ahí, me lo acabas de soltar."
    },
    {
      "start": 83.75999999999999,
      "end": 84.75999999999999,
      "speaker": "SPEAKER_00",
      "text": "Es que nos ha clasificado Cabo Verde."
    },
    {
      "start": 84.75999999999999,
      "end": 85.75999999999999,
      "speaker": "SPEAKER_00",
      "text": "Tarjeta amarilla, tarjeta amarilla."
    },
    {
      "start": 85.75999999999999,
      "end": 87.6,
      "speaker": "SPEAKER_00",
      "text": "Vamos con el ranking."
    },
    {
      "start": 87.6,
      "end": 95.8,
      "speaker": "SPEAKER_00",
      "text": "En décima posición hemos querido situar a una selección que no tiene una buena racha,"
    },
    {
      "start": 95.8,
      "end": 99.64,
      "speaker": "SPEAKER_00",
      "text": "pero que antes de la Copa América pintaba realmente bien."
    },
    {
      "start": 99.64,
      "end": 103.16,
      "speaker": "SPEAKER_00",
      "text": "Yo sigo creyendo que es una de las 10 favoritas a ganar el Mundial."
    },
    {
      "start": 103.16,
      "end": 105.84,
      "speaker": "SPEAKER_00",
      "text": "Es la selección uruguaya."
    },
    {
      "start": 105.84,
      "end": 107.64,
      "speaker": "SPEAKER_03",
      "text": "No, no, no debería estar."
    },
    {
      "start": 107.64,
      "end": 110.04,
      "speaker": "SPEAKER_03",
      "text": "Es imposible que gane Uruguay en Mundial."
    },
    {
      "start": 110.04,
      "end": 111.24,
      "speaker": "SPEAKER_03",
      "text": "Pero más allá del contra agafe."
    },
    {
      "start": 111.24,
      "end": 112.24,
      "speaker": "SPEAKER_03",
      "text": "Es imposible."
    },
    {
      "start": 112.24,
      "end": 113.24,
      "speaker": "SPEAKER_03",
      "text": "Pero en el ranking."
    },
    {
      "start": 113.24,
      "end": 114.6,
      "speaker": "SPEAKER_03",
      "text": "No puede estar, no puede ganar Uruguay."
    },
    {
      "start": 114.6,
      "end": 115.6,
      "speaker": "SPEAKER_03",
      "text": "Pero más allá del contra agafe."
    },
    {
      "start": 115.6,
      "end": 116.6,
      "speaker": "SPEAKER_03",
      "text": "No puede estar."
    },
    {
      "start": 116.6,
      "end": 117.6,
      "speaker": "SPEAKER_03",
      "text": "¿Está mal Uruguay?"
    },
    {
      "start": 117.6,
      "end": 118.6,
      "speaker": "SPEAKER_03",
      "text": "¿Tú es la que no querías que estuviera?"
    },
    {
      "start": 118.6,
      "end": 123.48,
      "speaker": "SPEAKER_03",
      "text": "No, no, es que de hecho, candidata clara a la primera ronda fuera."
    },
    {
      "start": 123.48,
      "end": 126.68,
      "speaker": "SPEAKER_03",
      "text": "Es lo que viene pasando últimamente, ¿pero crees que va a volver a pasar?"
    },
    {
      "start": 126.68,
      "end": 130.84,
      "speaker": "SPEAKER_03",
      "text": "Eso es mentira, pero yo creo que ya está, no ya está, se acaba Uruguay."
    },
    {
      "start": 130.84,
      "end": 135.64,
      "speaker": "SPEAKER_00",
      "text": "Vale, voy a ir al fútbol entonces, de Giano, Nau, o sea, Adri."
    },
    {
      "start": 135.64,
      "end": 140.0,
      "speaker": "SPEAKER_02",
      "text": "Yo tengo una sensación con la selección uruguaya que es, creo que por las imágenes"
    },
    {
      "start": 140.0,
      "end": 144.27999999999997,
      "speaker": "SPEAKER_02",
      "text": "que hemos podido ver de la celebración de la clasificación, se han limado las perezas"
    },
    {
      "start": 144.27999999999997,
      "end": 148.35999999999999,
      "speaker": "SPEAKER_02",
      "text": "entre cuerpo técnico y grupo, que eso parecía bastante relevante."
    },
    {
      "start": 148.35999999999999,
      "end": 153.0,
      "speaker": "SPEAKER_02",
      "text": "Parecía un poco guerra civil, acordáos en el primer parón de 2024."
    },
    {
      "start": 153.0,
      "end": 156.23999999999998,
      "speaker": "SPEAKER_02",
      "text": "En definitiva, parecía que se iban a complicar mucho las cosas."
    },
    {
      "start": 156.23999999999998,
      "end": 159.44,
      "speaker": "SPEAKER_02",
      "text": "Ha ganado tres partidos desde la Copa América, eso sí que es verdad."
    },
    {
      "start": 159.44,
      "end": 162.2,
      "speaker": "SPEAKER_02",
      "text": "Ha conseguido la clasificación un poco… ¿Tres de cuántos?"
    },
    {
      "start": 162.2,
      "end": 163.2,
      "speaker": "SPEAKER_02",
      "text": "De 12."
    },
    {
      "start": 163.23999999999998,
      "end": 165.6,
      "speaker": "SPEAKER_02",
      "text": "Le ha faltado media convocatoria."
    },
    {
      "start": 167.0,
      "end": 170.2,
      "speaker": "SPEAKER_02",
      "text": "Y en 2025 ha ganado dos partidos, ha empatado dos y ha perdido dos."
    },
    {
      "start": 170.2,
      "end": 171.79999999999998,
      "speaker": "SPEAKER_02",
      "text": "O sea, ha hecho todo perfecto."
    },
    {
      "start": 171.79999999999998,
      "end": 174.39999999999998,
      "speaker": "SPEAKER_02",
      "text": "Para mí, sensaciones que creo que pueden ir a mejor."
    },
    {
      "start": 174.39999999999998,
      "end": 177.04,
      "speaker": "SPEAKER_02",
      "text": "Una vez ya se ha pasado ese proceso de clasificación…"
    },
    {
      "start": 177.04,
      "end": 178.04,
      "speaker": "SPEAKER_02",
      "text": "Te liberas."
    },
    {
      "start": 178.04,
      "end": 180.04,
      "speaker": "SPEAKER_02",
      "text": "… y que creo que es una selección que puede llegar bien."
    },
    {
      "start": 180.04,
      "end": 181.04,
      "speaker": "SPEAKER_02",
      "text": "Ahora bien."
    },
    {
      "start": 181.04,
      "end": 185.35999999999999,
      "speaker": "SPEAKER_02",
      "text": "No me parece que tampoco tenga un jugador individual que le alce."
    },
    {
      "start": 185.35999999999999,
      "end": 189.51999999999998,
      "speaker": "SPEAKER_00",
      "text": "A mí es la selección que más me… Evidentemente, por eso está décima."
    },
    {
      "start": 189.56,
      "end": 193.36,
      "speaker": "SPEAKER_00",
      "text": "Aquí podía notar diferentes selecciones, pero yo sigo creyendo."
    },
    {
      "start": 193.36,
      "end": 195.76000000000002,
      "speaker": "SPEAKER_00",
      "text": "Es que me gustó mucho Uruguay antes de la Copa América."
    },
    {
      "start": 195.76000000000002,
      "end": 198.24,
      "speaker": "SPEAKER_00",
      "text": "Esos partidos contra Brasil, contra Argentina."
    },
    {
      "start": 199.04000000000002,
      "end": 202.32000000000002,
      "speaker": "SPEAKER_00",
      "text": "Luego es Uruguay, tiene esa tradición, hay que ganarla."
    },
    {
      "start": 203.32000000000002,
      "end": 206.0,
      "speaker": "SPEAKER_00",
      "text": "Bueno, yo creo que tiene que estar aquí, pero no."
    },
    {
      "start": 206.0,
      "end": 207.88,
      "speaker": "SPEAKER_00",
      "text": "Con muchos equipos."
    },
    {
      "start": 207.88,
      "end": 212.24,
      "speaker": "SPEAKER_01",
      "text": "Quiero creer en esta selección uruguaya, pero creo que si a alguien le sienta bien,"
    },
    {
      "start": 212.24,
      "end": 216.0,
      "speaker": "SPEAKER_01",
      "text": "llegar fuera de este power ranking al Mundial, es la selección uruguaya."
    },
    {
      "start": 216.0,
      "end": 217.36,
      "speaker": "SPEAKER_00",
      "text": "También te digo, está décima."
    },
    {
      "start": 217.4,
      "end": 220.8,
      "speaker": "SPEAKER_01",
      "text": "Bueno, bueno, pero que igual el Nadal Mirandas ha descrémado el 15º puesto."
    },
    {
      "start": 220.8,
      "end": 221.8,
      "speaker": "SPEAKER_01",
      "text": "No, no, no."
    },
    {
      "start": 221.8,
      "end": 222.8,
      "speaker": "SPEAKER_01",
      "text": "A lo Bajini."
    },
    {
      "start": 222.8,
      "end": 223.8,
      "speaker": "SPEAKER_03",
      "text": "No creo que…"
    },
    {
      "start": 223.8,
      "end": 224.8,
      "speaker": "SPEAKER_01",
      "text": "Acedo al verde en el flyer, no, no."
    },
    {
      "start": 224.8,
      "end": 225.8,
      "speaker": "SPEAKER_00",
      "text": "A lo Bajini."
    },
    {
      "start": 225.8,
      "end": 226.8,
      "speaker": "SPEAKER_00",
      "text": "A lo Bajini."
    },
    {
      "start": 226.8,
      "end": 227.8,
      "speaker": "SPEAKER_00",
      "text": "En novena posición…"
    },
    {
      "start": 227.8,
      "end": 228.8,
      "speaker": "SPEAKER_00",
      "text": "Si arruinan a la navia, es que no puede ser…"
    },
    {
      "start": 228.8,
      "end": 232.48000000000002,
      "speaker": "SPEAKER_00",
      "text": "En novena posición tenemos a Marruecos."
    },
    {
      "start": 232.48000000000002,
      "end": 239.24,
      "speaker": "SPEAKER_00",
      "text": "Una selección que no aparece en la mayoría de… Nos hemos ido a ver casas de apuestas,"
    },
    {
      "start": 239.24,
      "end": 243.20000000000002,
      "speaker": "SPEAKER_00",
      "text": "pronósticos también por… Oye, bichear y hacernos honerar de cómo ven las cosas,"
    },
    {
      "start": 243.20000000000002,
      "end": 246.52,
      "speaker": "SPEAKER_00",
      "text": "no ya en España, sino en Inglaterra, en Francia…"
    },
    {
      "start": 246.52,
      "end": 248.04000000000002,
      "speaker": "SPEAKER_02",
      "text": "En Estados Unidos con el tema del…"
    },
    {
      "start": 248.04000000000002,
      "end": 249.04000000000002,
      "speaker": "SPEAKER_00",
      "text": "Exactamente."
    },
    {
      "start": 249.04000000000002,
      "end": 251.0,
      "speaker": "SPEAKER_00",
      "text": "Marruecos no suele estar en el top 10."
    },
    {
      "start": 251.0,
      "end": 258.52,
      "speaker": "SPEAKER_00",
      "text": "Y es verdad que su nivel y su participación en el pasado Mundial tuvo parte de Noticiablo"
    },
    {
      "start": 258.52,
      "end": 260.08,
      "speaker": "SPEAKER_00",
      "text": "y de Sorpresa."
    },
    {
      "start": 260.08,
      "end": 265.12,
      "speaker": "SPEAKER_00",
      "text": "Pero yo creo que luego su rendimiento no fue casual, creo que ha ido acumulando noticias"
    },
    {
      "start": 265.12,
      "end": 270.96000000000004,
      "speaker": "SPEAKER_00",
      "text": "positivas, creo que también es un colectivo super competitivo y creo que sin lugar a dudas"
    },
    {
      "start": 270.96000000000004,
      "end": 274.8,
      "speaker": "SPEAKER_00",
      "text": "ahora mismo es la mejor selección africana a pesar de que no hiciese una gran Copa África."
    },
    {
      "start": 274.88,
      "end": 278.52000000000004,
      "speaker": "SPEAKER_02",
      "text": "No, no hicieron una gran Copa África, eliminaron Sudáfrica de hecho."
    },
    {
      "start": 278.52000000000004,
      "end": 282.64,
      "speaker": "SPEAKER_02",
      "text": "Estuve viendo ayer precisamente la inauguración del nuevo estadio y demás, ese Marruecos-Níger"
    },
    {
      "start": 282.64,
      "end": 284.56,
      "speaker": "SPEAKER_02",
      "text": "y me encantó la selección marroquí."
    },
    {
      "start": 284.56,
      "end": 289.8,
      "speaker": "SPEAKER_02",
      "text": "Laterales abiertos, tiene un lateral izquierdo que es nuevo, que tiene Ben…"
    },
    {
      "start": 289.8,
      "end": 290.8,
      "speaker": "SPEAKER_02",
      "text": "Belambani."
    },
    {
      "start": 290.8,
      "end": 291.8,
      "speaker": "SPEAKER_02",
      "text": "Belambani ese."
    },
    {
      "start": 291.8,
      "end": 296.92,
      "speaker": "SPEAKER_02",
      "text": "Muy abiertos, luego por dentro junta muchísimo talento, es Sofiano Amrabat el pivote y a"
    },
    {
      "start": 296.92,
      "end": 300.56,
      "speaker": "SPEAKER_02",
      "text": "partir de ahí Ben Seguir, Brahim, el Villalcan…"
    },
    {
      "start": 300.56,
      "end": 304.72,
      "speaker": "SPEAKER_00",
      "text": "No, él tiene seguramente al mejor jugador que es madrileño, pero evidentemente jugaba"
    },
    {
      "start": 304.72,
      "end": 308.16,
      "speaker": "SPEAKER_00",
      "text": "con Marruecos, el mejor jugador africano, que es Arraja Kimi."
    },
    {
      "start": 308.16,
      "end": 310.64000000000004,
      "speaker": "SPEAKER_00",
      "text": "Sí, Arraja Kimi, que juega muy abierto pero tiene libertad."
    },
    {
      "start": 310.64000000000004,
      "end": 314.32000000000005,
      "speaker": "SPEAKER_00",
      "text": "Es verdad que está en una posición quizás no tan determinante, pero es que hemos visto"
    },
    {
      "start": 314.32000000000005,
      "end": 315.92,
      "speaker": "SPEAKER_00",
      "text": "a Raph ser determinante desde esa posición."
    },
    {
      "start": 315.92,
      "end": 320.20000000000005,
      "speaker": "SPEAKER_03",
      "text": "Hay un chaval afincado en Liverpool que tendría algo que decir a este respecto."
    },
    {
      "start": 320.20000000000005,
      "end": 324.16,
      "speaker": "SPEAKER_03",
      "text": "Sí, pero quizá por formalizar."
    },
    {
      "start": 324.16,
      "end": 326.88000000000005,
      "speaker": "SPEAKER_03",
      "text": "No está en el power ranking, pero…"
    },
    {
      "start": 326.88000000000005,
      "end": 328.88000000000005,
      "speaker": "SPEAKER_00",
      "text": "Egipto se pudo clasificar ayer y el punto cero."
    },
    {
      "start": 328.88000000000005,
      "end": 331.76000000000005,
      "speaker": "SPEAKER_00",
      "text": "Creo que… es que estaba pensando yo en el balón de oro sobre todo, creo que van a estar"
    },
    {
      "start": 331.76000000000005,
      "end": 334.36,
      "speaker": "SPEAKER_02",
      "text": "en una posición similar, pero sí, Mohamed Salah evidentemente está ahí."
    },
    {
      "start": 334.36,
      "end": 336.36,
      "speaker": "SPEAKER_02",
      "text": "Ibarri, por ejemplo, ha nacido en Tarragas…"
    },
    {
      "start": 336.36,
      "end": 337.36,
      "speaker": "SPEAKER_02",
      "text": "Muy bueno."
    },
    {
      "start": 337.36,
      "end": 338.36,
      "speaker": "SPEAKER_02",
      "text": "Muy bueno."
    },
    {
      "start": 338.36,
      "end": 342.64,
      "speaker": "SPEAKER_02",
      "text": "Metió dos goles contra Níger de nueve prácticamente y una selección que para mí tiene muchísimos"
    },
    {
      "start": 342.64,
      "end": 344.48,
      "speaker": "SPEAKER_02",
      "text": "recursos para hacer un gran mundial."
    },
    {
      "start": 344.48,
      "end": 348.6,
      "speaker": "SPEAKER_00",
      "text": "Está Bonu, que lo vimos en el Mundial de Clubes, que fue una fortaleza."
    },
    {
      "start": 348.6,
      "end": 350.6,
      "speaker": "SPEAKER_00",
      "text": "Sabemos que el estilo de Marruecos es el que es."
    },
    {
      "start": 350.6,
      "end": 351.6,
      "speaker": "SPEAKER_00",
      "text": "Lo sabemos por desgracia, además."
    },
    {
      "start": 351.6,
      "end": 352.6,
      "speaker": "SPEAKER_01",
      "text": "Sí, sí."
    },
    {
      "start": 352.6,
      "end": 353.6,
      "speaker": "SPEAKER_01",
      "text": "Lo sufrimos en nuestras carnes."
    },
    {
      "start": 353.6,
      "end": 357.8,
      "speaker": "SPEAKER_01",
      "text": "Yo creo que esta es la selección que le va a sorprender a la gente, que aparezca Marruecos"
    },
    {
      "start": 357.8,
      "end": 361.92,
      "speaker": "SPEAKER_01",
      "text": "en esta clasificación de las 10 favoritas, que aparezca como novena, pero claro, uno"
    },
    {
      "start": 361.92,
      "end": 365.28000000000003,
      "speaker": "SPEAKER_01",
      "text": "repasa la fase de clasificación y se la está dominando por completo."
    },
    {
      "start": 365.28000000000003,
      "end": 366.28000000000003,
      "speaker": "SPEAKER_01",
      "text": "Son 21 puntos."
    },
    {
      "start": 366.28000000000003,
      "end": 367.72,
      "speaker": "SPEAKER_03",
      "text": "El finalista del pasado mundial también."
    },
    {
      "start": 367.72,
      "end": 368.72,
      "speaker": "SPEAKER_03",
      "text": "Siete victorias."
    },
    {
      "start": 368.72,
      "end": 369.72,
      "speaker": "SPEAKER_03",
      "text": "21 goles, por favor."
    },
    {
      "start": 369.72,
      "end": 370.72,
      "speaker": "SPEAKER_03",
      "text": "Dos en total."
    },
    {
      "start": 370.72,
      "end": 374.24,
      "speaker": "SPEAKER_03",
      "text": "Ha cambiado mucho y les ha cambiado para mal, yo creo, a los grandes jugadores de esa generación."
    },
    {
      "start": 374.24,
      "end": 377.92,
      "speaker": "SPEAKER_00",
      "text": "Aunque vete tú a saber si como en ese mundial que rindieron como nadie, porque esto nos"
    },
    {
      "start": 377.92,
      "end": 381.64,
      "speaker": "SPEAKER_00",
      "text": "lo dice siempre Alberto Diogo y a poco que repases…"
    },
    {
      "start": 381.64,
      "end": 384.76,
      "speaker": "SPEAKER_00",
      "text": "Que ya no es fútbol, es casi cultura, ¿no?"
    },
    {
      "start": 384.76,
      "end": 385.76,
      "speaker": "SPEAKER_00",
      "text": "O social, sí."
    },
    {
      "start": 385.76,
      "end": 387.92,
      "speaker": "SPEAKER_00",
      "text": "O sociopolítica, no sé cómo llamarlo."
    },
    {
      "start": 387.92,
      "end": 392.32,
      "speaker": "SPEAKER_00",
      "text": "El sentimiento del aficionado marroquí, del futbolista marroquí es súper potente."
    },
    {
      "start": 392.32,
      "end": 393.32,
      "speaker": "SPEAKER_00",
      "text": "Brutal."
    },
    {
      "start": 393.32,
      "end": 396.8,
      "speaker": "SPEAKER_00",
      "text": "Mientras muchos jugadores nacidos en Europa, pero de ascendencia y origen africano decían"
    },
    {
      "start": 396.8,
      "end": 400.56,
      "speaker": "SPEAKER_00",
      "text": "jugar con selecciones europeas, Marruecos retiene casi todo su talento."
    },
    {
      "start": 400.56,
      "end": 402.04,
      "speaker": "SPEAKER_00",
      "text": "Por suerte se le ha escapado el mejor."
    },
    {
      "start": 402.04,
      "end": 403.04,
      "speaker": "SPEAKER_00",
      "text": "Bueno, mira…"
    },
    {
      "start": 403.04,
      "end": 404.04,
      "speaker": "SPEAKER_00",
      "text": "Que podía haber jugado ahí, que es la mía mal."
    },
    {
      "start": 404.04,
      "end": 405.04,
      "speaker": "SPEAKER_00",
      "text": "Sí."
    },
    {
      "start": 405.04,
      "end": 410.48,
      "speaker": "SPEAKER_00",
      "text": "Pero la mayoría de futbolistas afectan jugar con Marruecos por delante de Francia, Bélgica…"
    },
    {
      "start": 410.48,
      "end": 412.68,
      "speaker": "SPEAKER_02",
      "text": "Marruecos tiene dos laterales de derecho nacidos en España."
    },
    {
      "start": 412.68,
      "end": 414.96000000000004,
      "speaker": "SPEAKER_02",
      "text": "O sea, que son Arraza y Omar Gimárez."
    },
    {
      "start": 414.96000000000004,
      "end": 416.16,
      "speaker": "SPEAKER_00",
      "text": "Y que Arraza no dijimos."
    },
    {
      "start": 416.16,
      "end": 417.48,
      "speaker": "SPEAKER_00",
      "text": "No, bueno, el rollo Brahim."
    },
    {
      "start": 417.48,
      "end": 418.48,
      "speaker": "SPEAKER_00",
      "text": "No, bueno…"
    },
    {
      "start": 418.48,
      "end": 419.48,
      "speaker": "SPEAKER_03",
      "text": "No, no, no."
    },
    {
      "start": 419.48,
      "end": 421.40000000000003,
      "speaker": "SPEAKER_03",
      "text": "Arraza lo quería del fútbol español y Arraza quiso jugar con Marruecos."
    },
    {
      "start": 421.40000000000003,
      "end": 425.64000000000004,
      "speaker": "SPEAKER_03",
      "text": "Estoy hablando de memoria, pero de las 32 selecciones que jugaban en 2022, creo que"
    },
    {
      "start": 425.64000000000004,
      "end": 429.8,
      "speaker": "SPEAKER_03",
      "text": "Marruecos era la selección que tenía más futbolistas nacidos fuera del territorio marroquí."
    },
    {
      "start": 429.8,
      "end": 435.28000000000003,
      "speaker": "SPEAKER_00",
      "text": "Y te decía eso porque tienen un punto competitivo que a mí me recuerda a lo sudamericano."
    },
    {
      "start": 435.28000000000003,
      "end": 436.28000000000003,
      "speaker": "SPEAKER_00",
      "text": "El sentimiento ese…"
    },
    {
      "start": 436.28000000000003,
      "end": 441.16,
      "speaker": "SPEAKER_00",
      "text": "No sé si nacionalista o de jugar algo más que fútbol que sacó lo mejor de Anrabat,"
    },
    {
      "start": 441.16,
      "end": 443.92,
      "speaker": "SPEAKER_00",
      "text": "de Amalai, de Aunaji porque desde entonces ninguno ha estado de todos."
    },
    {
      "start": 443.92,
      "end": 446.24,
      "speaker": "SPEAKER_02",
      "text": "Y un detalle muy importante con las selecciones africanas."
    },
    {
      "start": 446.32,
      "end": 448.16,
      "speaker": "SPEAKER_02",
      "text": "Hay Copa de África justo antes de Mundial."
    },
    {
      "start": 448.16,
      "end": 450.92,
      "speaker": "SPEAKER_02",
      "text": "O sea, en el período diciembre-tenero hay Copa de África."
    },
    {
      "start": 450.92,
      "end": 451.92,
      "speaker": "SPEAKER_02",
      "text": "Eso es tremendo."
    },
    {
      "start": 451.92,
      "end": 452.92,
      "speaker": "SPEAKER_00",
      "text": "O sea, hay que tener…"
    },
    {
      "start": 452.92,
      "end": 453.92,
      "speaker": "SPEAKER_00",
      "text": "Es tremendo y es negativo."
    },
    {
      "start": 453.92,
      "end": 457.24,
      "speaker": "SPEAKER_02",
      "text": "Bueno, se han desplazado por motivos obvios."
    },
    {
      "start": 457.24,
      "end": 458.24,
      "speaker": "SPEAKER_00",
      "text": "Sí, sí, sí."
    },
    {
      "start": 458.24,
      "end": 466.56,
      "speaker": "SPEAKER_00",
      "text": "En octava posición a mí me sorprende ver también tan lejos del top 3, podríamos decir."
    },
    {
      "start": 466.56,
      "end": 468.88,
      "speaker": "SPEAKER_00",
      "text": "Pero ha bajado posiciones en este parón."
    },
    {
      "start": 468.88,
      "end": 471.2,
      "speaker": "SPEAKER_00",
      "text": "Es Alemania, Adri."
    },
    {
      "start": 471.2,
      "end": 475.92,
      "speaker": "SPEAKER_00",
      "text": "El toque de atención de Nagelsmann, los silbidos y abucheos el otro día ante Irlanda del Norte."
    },
    {
      "start": 476.56,
      "end": 481.52000000000004,
      "speaker": "SPEAKER_00",
      "text": "Las sensaciones que está transmitiendo una selección que se puede ir a la repesca perfectamente."
    },
    {
      "start": 481.52000000000004,
      "end": 482.52000000000004,
      "speaker": "SPEAKER_00",
      "text": "Uf."
    },
    {
      "start": 482.52000000000004,
      "end": 484.96000000000004,
      "speaker": "SPEAKER_01",
      "text": "La retirada de Kroos, la adhesión de Musiala."
    },
    {
      "start": 484.96000000000004,
      "end": 485.96000000000004,
      "speaker": "SPEAKER_01",
      "text": "Uf."
    },
    {
      "start": 485.96000000000004,
      "end": 487.40000000000003,
      "speaker": "SPEAKER_01",
      "text": "Son muchos factores los que están…"
    },
    {
      "start": 487.40000000000003,
      "end": 490.44,
      "speaker": "SPEAKER_00",
      "text": "Yo creo que Alemania va a subir posiciones según vayamos haciendo este powerranken de"
    },
    {
      "start": 490.44,
      "end": 492.0,
      "speaker": "SPEAKER_00",
      "text": "aquí a junio."
    },
    {
      "start": 492.0,
      "end": 493.64,
      "speaker": "SPEAKER_00",
      "text": "Pero ahora creo que tiene que estar aquí."
    },
    {
      "start": 493.64,
      "end": 494.96000000000004,
      "speaker": "SPEAKER_01",
      "text": "El momento de Antonio Rüdiger."
    },
    {
      "start": 494.96000000000004,
      "end": 499.48,
      "speaker": "SPEAKER_01",
      "text": "Son muchos factores que invitan a no ser optimistas con Alemania ahora mismo."
    },
    {
      "start": 499.48,
      "end": 504.16,
      "speaker": "SPEAKER_01",
      "text": "Y yo creo que el tirón de orejas del otro día de Nagelsmann, público apuntando directamente"
    },
    {
      "start": 504.16,
      "end": 505.16,
      "speaker": "SPEAKER_01",
      "text": "a la plantilla."
    },
    {
      "start": 505.16,
      "end": 509.0,
      "speaker": "SPEAKER_01",
      "text": "Es un mensaje de alarma importante porque él es el primero que huele, el primero que detecta"
    },
    {
      "start": 509.0,
      "end": 513.0,
      "speaker": "SPEAKER_01",
      "text": "que como si ganase las cosas, puede haber batacazo Alemania en el Mundial."
    },
    {
      "start": 513.0,
      "end": 515.8000000000001,
      "speaker": "SPEAKER_02",
      "text": "En los últimos cinco partidos, una victoria, un empate, tres derrotas."
    },
    {
      "start": 515.8000000000001,
      "end": 517.8000000000001,
      "speaker": "SPEAKER_02",
      "text": "Las malas sensaciones que acumula."
    },
    {
      "start": 517.8000000000001,
      "end": 520.8000000000001,
      "speaker": "SPEAKER_02",
      "text": "Yo el partido de Irlanda del Norte lo estuve viendo y…"
    },
    {
      "start": 520.8000000000001,
      "end": 523.8000000000001,
      "speaker": "SPEAKER_02",
      "text": "Es que me daba una sensación de que el equipo no avanzaba."
    },
    {
      "start": 523.8000000000001,
      "end": 528.4,
      "speaker": "SPEAKER_02",
      "text": "Que se organizaban tres centrales con carrileros, sobre todo el de la derecha más largo que"
    },
    {
      "start": 528.4,
      "end": 530.96,
      "speaker": "SPEAKER_02",
      "text": "era Lebelin, el futbolista este tan interesante del Stuttgart."
    },
    {
      "start": 530.96,
      "end": 533.9200000000001,
      "speaker": "SPEAKER_02",
      "text": "Y muchos problemas para organizar el juego."
    },
    {
      "start": 533.9200000000001,
      "end": 537.2,
      "speaker": "SPEAKER_02",
      "text": "Kimmich y Pascall Gross no terminan de cuajar del todo."
    },
    {
      "start": 537.2,
      "end": 538.9200000000001,
      "speaker": "SPEAKER_02",
      "text": "Me dejó algo de dudas."
    },
    {
      "start": 538.9200000000001,
      "end": 543.36,
      "speaker": "SPEAKER_03",
      "text": "De hecho, la medida de puntos empieza a parecerse mucho a la de la era Flick, que fue una era"
    },
    {
      "start": 543.36,
      "end": 545.9200000000001,
      "speaker": "SPEAKER_03",
      "text": "también muy complicada."
    },
    {
      "start": 545.9200000000001,
      "end": 549.44,
      "speaker": "SPEAKER_03",
      "text": "Flick no se pudo llevar al 22 a Florian Birch, que estaba recuperado pero recién recuperado."
    },
    {
      "start": 549.44,
      "end": 552.0400000000001,
      "speaker": "SPEAKER_03",
      "text": "Da la sensación de que el escenario con Musiala va a ser similar."
    },
    {
      "start": 552.0400000000001,
      "end": 554.8000000000001,
      "speaker": "SPEAKER_03",
      "text": "Que va a llegar sano con la de la alta médica."
    },
    {
      "start": 554.8000000000001,
      "end": 555.8000000000001,
      "speaker": "SPEAKER_03",
      "text": "Pero el postito."
    },
    {
      "start": 556.8,
      "end": 562.0,
      "speaker": "SPEAKER_03",
      "text": "Y bueno, tiene que cambiar mucho la situación en Alemania porque salvo que Angelos Thieler"
    },
    {
      "start": 562.0,
      "end": 565.9599999999999,
      "speaker": "SPEAKER_03",
      "text": "dé un paso adelante muy bestia, en el centro del campo creo que va a ir muy coja."
    },
    {
      "start": 565.9599999999999,
      "end": 569.12,
      "speaker": "SPEAKER_03",
      "text": "Y lo del lateral derecho es que desde la retirada de Philipp Lange no termina de encontrar una"
    },
    {
      "start": 569.12,
      "end": 570.12,
      "speaker": "SPEAKER_03",
      "text": "alternativa."
    },
    {
      "start": 570.12,
      "end": 573.4799999999999,
      "speaker": "SPEAKER_00",
      "text": "Es que te iba a decir, Alex, que de hecho ese partido que mencionabas de Alemania le ha"
    },
    {
      "start": 573.4799999999999,
      "end": 578.0,
      "speaker": "SPEAKER_00",
      "text": "hecho en el ranking que nosotros íbamos proyectando perder una posición respecto a la séptima"
    },
    {
      "start": 578.0,
      "end": 581.4799999999999,
      "speaker": "SPEAKER_00",
      "text": "clasificada que nosotros situamos que es Países Bajos."
    },
    {
      "start": 581.4799999999999,
      "end": 584.0799999999999,
      "speaker": "SPEAKER_00",
      "text": "Países Bajos tampoco va…"
    },
    {
      "start": 584.0799999999999,
      "end": 585.76,
      "speaker": "SPEAKER_00",
      "text": "Países Bajos no va sobradísima."
    },
    {
      "start": 585.8,
      "end": 586.8,
      "speaker": "SPEAKER_00",
      "text": "A lo bajiri."
    },
    {
      "start": 586.8,
      "end": 588.84,
      "speaker": "SPEAKER_00",
      "text": "Va un poquito así."
    },
    {
      "start": 588.84,
      "end": 594.68,
      "speaker": "SPEAKER_00",
      "text": "Tampoco tiene ninguna participación super destacada en los últimos años."
    },
    {
      "start": 594.68,
      "end": 595.68,
      "speaker": "SPEAKER_00",
      "text": "No."
    },
    {
      "start": 595.68,
      "end": 598.28,
      "speaker": "SPEAKER_00",
      "text": "Pero creo que es una selección que es estable."
    },
    {
      "start": 598.28,
      "end": 600.08,
      "speaker": "SPEAKER_00",
      "text": "¿Es de las máximas favoritas?"
    },
    {
      "start": 600.08,
      "end": 601.08,
      "speaker": "SPEAKER_00",
      "text": "No."
    },
    {
      "start": 601.08,
      "end": 603.08,
      "speaker": "SPEAKER_00",
      "text": "Pero creo que es lógica esa última posición."
    },
    {
      "start": 603.08,
      "end": 606.84,
      "speaker": "SPEAKER_02",
      "text": "El Mundial elimina a Argentina en ese partido llevado hasta la tanda de penaltis."
    },
    {
      "start": 606.84,
      "end": 607.84,
      "speaker": "SPEAKER_02",
      "text": "Ya pasa."
    },
    {
      "start": 607.84,
      "end": 609.52,
      "speaker": "SPEAKER_02",
      "text": "Que mira, bobo."
    },
    {
      "start": 609.52,
      "end": 613.64,
      "speaker": "SPEAKER_02",
      "text": "Y en la Eurocopa, bueno, yo creo que intentó algo más."
    },
    {
      "start": 613.68,
      "end": 618.08,
      "speaker": "SPEAKER_02",
      "text": "Sobre todo con esta generación joven, Berger Brugge en portería, etcétera, etcétera,"
    },
    {
      "start": 618.08,
      "end": 622.96,
      "speaker": "SPEAKER_02",
      "text": "pero es un equipo que para mí sigue teniendo un problema bastante importante y es que el"
    },
    {
      "start": 622.96,
      "end": 625.3199999999999,
      "speaker": "SPEAKER_02",
      "text": "gol se sigue centrando en la figura de Memphis."
    },
    {
      "start": 625.3199999999999,
      "end": 626.92,
      "speaker": "SPEAKER_00",
      "text": "Máximo goleador ya histórico."
    },
    {
      "start": 626.92,
      "end": 629.36,
      "speaker": "SPEAKER_00",
      "text": "Es verdad que Rangers está creciendo."
    },
    {
      "start": 629.36,
      "end": 631.24,
      "speaker": "SPEAKER_01",
      "text": "Es verdad que en estos torneos GACPOO se crece."
    },
    {
      "start": 631.24,
      "end": 634.24,
      "speaker": "SPEAKER_00",
      "text": "Bueno, y Dan Frisby te cuento que es verdad que viene de una gran Champions pero Dan Frisby"
    },
    {
      "start": 634.24,
      "end": 635.76,
      "speaker": "SPEAKER_00",
      "text": "es el jugador de selección por excelencia."
    },
    {
      "start": 635.76,
      "end": 636.76,
      "speaker": "SPEAKER_03",
      "text": "Totalmente."
    },
    {
      "start": 636.76,
      "end": 637.76,
      "speaker": "SPEAKER_03",
      "text": "Que luego se crece mucho."
    },
    {
      "start": 637.76,
      "end": 640.92,
      "speaker": "SPEAKER_03",
      "text": "De GACPOO contaban antes el Mundial del 22, que parece que lo podía hacer el Southampton,"
    },
    {
      "start": 640.92,
      "end": 642.92,
      "speaker": "SPEAKER_02",
      "text": "después del Mundial Liverpool."
    },
    {
      "start": 643.88,
      "end": 649.4799999999999,
      "speaker": "SPEAKER_01",
      "text": "Y es verdad que le está costando en según qué posiciones hacer el relevo generacional."
    },
    {
      "start": 649.4799999999999,
      "end": 651.9599999999999,
      "speaker": "SPEAKER_01",
      "text": "Creo que hay posiciones que quizás se están atascando un poco."
    },
    {
      "start": 651.9599999999999,
      "end": 653.28,
      "speaker": "SPEAKER_01",
      "text": "En las centrales van bien, por ejemplo."
    },
    {
      "start": 653.28,
      "end": 656.5999999999999,
      "speaker": "SPEAKER_01",
      "text": "Pero no es una selección que enamore, pero oye, está ahí."
    },
    {
      "start": 656.5999999999999,
      "end": 659.0799999999999,
      "speaker": "SPEAKER_01",
      "text": "Yo creo que el suelo lo está marcando."
    },
    {
      "start": 659.0799999999999,
      "end": 662.16,
      "speaker": "SPEAKER_00",
      "text": "En ese nivel medio alto, sexta posición."
    },
    {
      "start": 662.16,
      "end": 664.68,
      "speaker": "SPEAKER_02",
      "text": "A ver, se pone serio esto ya, eh."
    },
    {
      "start": 664.68,
      "end": 668.76,
      "speaker": "SPEAKER_00",
      "text": "Sí, aunque todavía no ha mejorado considerablemente."
    },
    {
      "start": 668.76,
      "end": 671.0,
      "speaker": "SPEAKER_00",
      "text": "Las apuestas le dan el segundo máximo favorito."
    },
    {
      "start": 671.96,
      "end": 673.96,
      "speaker": "SPEAKER_02",
      "text": "Confiarán mucho en Ancelotti."
    },
    {
      "start": 673.96,
      "end": 674.96,
      "speaker": "SPEAKER_00",
      "text": "Brasil."
    },
    {
      "start": 676.96,
      "end": 681.16,
      "speaker": "SPEAKER_00",
      "text": "Yo creo que las apuestas al final no dejan de ser pronósticos de la gente."
    },
    {
      "start": 681.16,
      "end": 685.8,
      "speaker": "SPEAKER_00",
      "text": "La casa de apuestas marca una cuota viendo lo que hay, pero luego el mercado sube y baja."
    },
    {
      "start": 685.8,
      "end": 689.92,
      "speaker": "SPEAKER_00",
      "text": "Un poco rollo bolsa según la confianza que tenga el aficionado."
    },
    {
      "start": 689.92,
      "end": 691.16,
      "speaker": "SPEAKER_00",
      "text": "Yo creo que es Brasil."
    },
    {
      "start": 691.16,
      "end": 693.24,
      "speaker": "SPEAKER_00",
      "text": "Que se le sitúa a Brasil porque es Brasil."
    },
    {
      "start": 693.24,
      "end": 694.84,
      "speaker": "SPEAKER_00",
      "text": "Más que por Ancelotti."
    },
    {
      "start": 694.84,
      "end": 696.64,
      "speaker": "SPEAKER_00",
      "text": "Ha tocado cosas."
    },
    {
      "start": 696.64,
      "end": 697.64,
      "speaker": "SPEAKER_00",
      "text": "Ganó el otro día."
    },
    {
      "start": 697.64,
      "end": 699.12,
      "speaker": "SPEAKER_00",
      "text": "A mí me gustó el partido."
    },
    {
      "start": 699.12,
      "end": 700.12,
      "speaker": "SPEAKER_00",
      "text": "El de Bolivia."
    },
    {
      "start": 700.24,
      "end": 701.24,
      "speaker": "SPEAKER_00",
      "text": "No lo he visto."
    },
    {
      "start": 701.24,
      "end": 704.04,
      "speaker": "SPEAKER_00",
      "text": "Y bueno, era un partido que no contaba, pero es una derrota de Brasil."
    },
    {
      "start": 704.04,
      "end": 708.6,
      "speaker": "SPEAKER_00",
      "text": "Y hay muchas dudas porque quién es el crack."
    },
    {
      "start": 708.6,
      "end": 710.6,
      "speaker": "SPEAKER_00",
      "text": "Los laterales."
    },
    {
      "start": 710.6,
      "end": 711.6,
      "speaker": "SPEAKER_00",
      "text": "El tema de los laterales."
    },
    {
      "start": 711.6,
      "end": 717.76,
      "speaker": "SPEAKER_00",
      "text": "La sensación además que como todo equipo grande carga con una losa de expectativas"
    },
    {
      "start": 717.76,
      "end": 722.84,
      "speaker": "SPEAKER_00",
      "text": "o incluso favoritismo, insisto, segundo máximo favorito, que no es coherente con lo que viene"
    },
    {
      "start": 722.84,
      "end": 724.76,
      "speaker": "SPEAKER_00",
      "text": "demostrando y eso es esa losa."
    },
    {
      "start": 724.76,
      "end": 729.24,
      "speaker": "SPEAKER_00",
      "text": "O sea, igual que Naguay se quería quitar el STD con Uruguay, Brasil no se lo puede quitar."
    },
    {
      "start": 729.36,
      "end": 733.16,
      "speaker": "SPEAKER_00",
      "text": "Y no tiene tanto talento como para llevar esa bitola de segundo favorito."
    },
    {
      "start": 733.16,
      "end": 736.92,
      "speaker": "SPEAKER_01",
      "text": "Tal y verdad que por las circunstancias Ancelotti no ha podido contar con todos los futbolistas"
    },
    {
      "start": 736.92,
      "end": 737.92,
      "speaker": "SPEAKER_01",
      "text": "que entendemos."
    },
    {
      "start": 737.92,
      "end": 740.52,
      "speaker": "SPEAKER_02",
      "text": "Ha llevado una lista un poco alternativa."
    },
    {
      "start": 740.52,
      "end": 742.12,
      "speaker": "SPEAKER_01",
      "text": "No los ha podido juntar todavía todos."
    },
    {
      "start": 742.12,
      "end": 744.88,
      "speaker": "SPEAKER_01",
      "text": "No sabemos muy bien qué pretende Ancelotti con los cracks."
    },
    {
      "start": 744.88,
      "end": 745.88,
      "speaker": "SPEAKER_01",
      "text": "Y que mucho tiempo no tiene."
    },
    {
      "start": 745.88,
      "end": 746.88,
      "speaker": "SPEAKER_01",
      "text": "De la selección."
    },
    {
      "start": 746.88,
      "end": 747.88,
      "speaker": "SPEAKER_01",
      "text": "También es cierto."
    },
    {
      "start": 747.88,
      "end": 749.8,
      "speaker": "SPEAKER_01",
      "text": "Me gustó por ejemplo el partidante de Chile."
    },
    {
      "start": 749.8,
      "end": 751.2,
      "speaker": "SPEAKER_01",
      "text": "A mí me gustó mucho yo a Pedro."
    },
    {
      "start": 751.2,
      "end": 752.2,
      "speaker": "SPEAKER_01",
      "text": "Juegando con nueve."
    },
    {
      "start": 752.2,
      "end": 753.8,
      "speaker": "SPEAKER_01",
      "text": "Me gustó mucho el futbolista del Chelsea."
    },
    {
      "start": 753.8,
      "end": 756.96,
      "speaker": "SPEAKER_01",
      "text": "Y justo me parece una noticia importante para el nueve de la selección."
    },
    {
      "start": 757.6800000000001,
      "end": 759.76,
      "speaker": "SPEAKER_02",
      "text": "A mí me falta un nueve más mandón en el área."
    },
    {
      "start": 759.76,
      "end": 760.76,
      "speaker": "SPEAKER_02",
      "text": "Quizá."
    },
    {
      "start": 760.76,
      "end": 761.96,
      "speaker": "SPEAKER_02",
      "text": "O sea que le pueda solimentar más partidos."
    },
    {
      "start": 761.96,
      "end": 765.6,
      "speaker": "SPEAKER_02",
      "text": "Es verdad que va a ir Brasil un poco a que sean los extremos los que me lo resuelvan."
    },
    {
      "start": 765.6,
      "end": 767.6,
      "speaker": "SPEAKER_02",
      "text": "La llegada desde atrás que tiene unos llegadores."
    },
    {
      "start": 767.6,
      "end": 768.96,
      "speaker": "SPEAKER_02",
      "text": "Rafael está jugando a media punta."
    },
    {
      "start": 768.96,
      "end": 769.96,
      "speaker": "SPEAKER_02",
      "text": "Claro, pero sí."
    },
    {
      "start": 769.96,
      "end": 774.88,
      "speaker": "SPEAKER_02",
      "text": "O sea, yo tengo un poco de dudas y hay una cosa en Brasil a la que se agarran."
    },
    {
      "start": 774.88,
      "end": 775.88,
      "speaker": "SPEAKER_02",
      "text": "A Casemiro."
    },
    {
      "start": 775.88,
      "end": 776.88,
      "speaker": "SPEAKER_02",
      "text": "No."
    },
    {
      "start": 776.88,
      "end": 777.88,
      "speaker": "SPEAKER_02",
      "text": "Casemiro es más de agarrada."
    },
    {
      "start": 777.88,
      "end": 780.2800000000001,
      "speaker": "SPEAKER_02",
      "text": "¿Cuál es el último mundial que ganó Brasil?"
    },
    {
      "start": 780.2800000000001,
      "end": 781.2800000000001,
      "speaker": "SPEAKER_02",
      "text": "Sí, evidentemente."
    },
    {
      "start": 781.2800000000001,
      "end": 782.2800000000001,
      "speaker": "SPEAKER_02",
      "text": "2002."
    },
    {
      "start": 782.2800000000001,
      "end": 783.2800000000001,
      "speaker": "SPEAKER_02",
      "text": "Pues esta es la pregunta."
    },
    {
      "start": 783.2800000000001,
      "end": 784.2800000000001,
      "speaker": "SPEAKER_02",
      "text": "Evidentemente."
    },
    {
      "start": 784.2800000000001,
      "end": 785.2800000000001,
      "speaker": "SPEAKER_02",
      "text": "Me ha encantado."
    },
    {
      "start": 785.6,
      "end": 786.6,
      "speaker": "SPEAKER_02",
      "text": "El que lo vi fue yo."
    },
    {
      "start": 786.6,
      "end": 787.6,
      "speaker": "SPEAKER_00",
      "text": "Que vosotros eras un hormíco."
    },
    {
      "start": 787.6,
      "end": 790.6,
      "speaker": "SPEAKER_02",
      "text": "Bueno, yo lo recuerdo perfectamente en Antena 3, comentado por Vicente del Bosque."
    },
    {
      "start": 790.6,
      "end": 793.6,
      "speaker": "SPEAKER_02",
      "text": "Por cierto, que lo da en vía digital y Antena 3, los partidos."
    },
    {
      "start": 793.6,
      "end": 794.6,
      "speaker": "SPEAKER_02",
      "text": "Eh…"
    },
    {
      "start": 794.6,
      "end": 795.6,
      "speaker": "SPEAKER_02",
      "text": "Toma ya."
    },
    {
      "start": 795.6,
      "end": 796.6,
      "speaker": "SPEAKER_02",
      "text": "Ahora vas y lo cascas."
    },
    {
      "start": 796.6,
      "end": 797.6,
      "speaker": "SPEAKER_02",
      "text": "El dato que necesitabas."
    },
    {
      "start": 797.6,
      "end": 798.6,
      "speaker": "SPEAKER_02",
      "text": "Ahora vas y lo cascas."
    },
    {
      "start": 798.6,
      "end": 801.6,
      "speaker": "SPEAKER_02",
      "text": "La peor eliminatoria de Brasil ha sido esta."
    },
    {
      "start": 801.6,
      "end": 804.6,
      "speaker": "SPEAKER_02",
      "text": "Pero la que tuvieron más derrotas también fue en la previa 2002."
    },
    {
      "start": 804.6,
      "end": 805.6,
      "speaker": "SPEAKER_02",
      "text": "Se agarran un poco a olla."
    },
    {
      "start": 805.6,
      "end": 808.6,
      "speaker": "SPEAKER_02",
      "text": "A ver si apretamos un poco los machos y nos da."
    },
    {
      "start": 808.6,
      "end": 810.6,
      "speaker": "SPEAKER_02",
      "text": "A ver, Ronaldo Nazario, dónde estás."
    },
    {
      "start": 810.6,
      "end": 811.6,
      "speaker": "SPEAKER_02",
      "text": "Y Rivaldo."
    },
    {
      "start": 811.6,
      "end": 813.6,
      "speaker": "SPEAKER_00",
      "text": "La selección de 2002 partía de muy abajo."
    },
    {
      "start": 813.9200000000001,
      "end": 814.9200000000001,
      "speaker": "SPEAKER_03",
      "text": "Y no convencía nadie."
    },
    {
      "start": 814.9200000000001,
      "end": 817.9200000000001,
      "speaker": "SPEAKER_03",
      "text": "La de 2010 con Dunga era un horror."
    },
    {
      "start": 817.9200000000001,
      "end": 820.9200000000001,
      "speaker": "SPEAKER_03",
      "text": "Y bueno, si no se le va la cabeza a Felipe Melo, estamos hablando de semifinales."
    },
    {
      "start": 820.9200000000001,
      "end": 822.9200000000001,
      "speaker": "SPEAKER_03",
      "text": "La de 2014 era otro horror."
    },
    {
      "start": 822.9200000000001,
      "end": 823.9200000000001,
      "speaker": "SPEAKER_03",
      "text": "Y hace semifinales."
    },
    {
      "start": 823.9200000000001,
      "end": 826.9200000000001,
      "speaker": "SPEAKER_03",
      "text": "Y bueno, y le mete el 7 porque también se queda Santiago Silve sin Neymar."
    },
    {
      "start": 826.9200000000001,
      "end": 827.9200000000001,
      "speaker": "SPEAKER_03",
      "text": "Siempre tiene que agarrarse."
    },
    {
      "start": 827.9200000000001,
      "end": 828.9200000000001,
      "speaker": "SPEAKER_03",
      "text": "Sí, sí, sí."
    },
    {
      "start": 828.9200000000001,
      "end": 829.9200000000001,
      "speaker": "SPEAKER_03",
      "text": "Y por eso la situamos esta."
    },
    {
      "start": 829.9200000000001,
      "end": 833.9200000000001,
      "speaker": "SPEAKER_03",
      "text": "Porque si fuera por la comparativa con Uruguay, los últimos tres partidos no podría estar"
    },
    {
      "start": 833.9200000000001,
      "end": 834.9200000000001,
      "speaker": "SPEAKER_03",
      "text": "ahí."
    },
    {
      "start": 834.9200000000001,
      "end": 835.9200000000001,
      "speaker": "SPEAKER_03",
      "text": "Por ejemplo."
    },
    {
      "start": 835.9200000000001,
      "end": 836.9200000000001,
      "speaker": "SPEAKER_03",
      "text": "Pero…"
    },
    {
      "start": 836.9200000000001,
      "end": 837.9200000000001,
      "speaker": "SPEAKER_03",
      "text": "Pero Uruguay no debería estar en el top 10."
    },
    {
      "start": 837.9200000000001,
      "end": 838.9200000000001,
      "speaker": "SPEAKER_03",
      "text": "No, no, no."
    },
    {
      "start": 838.9200000000001,
      "end": 839.9200000000001,
      "speaker": "SPEAKER_03",
      "text": "Uruguay…"
    },
    {
      "start": 839.9200000000001,
      "end": 840.9200000000001,
      "speaker": "SPEAKER_03",
      "text": "Y en Brasil tampoco."
    },
    {
      "start": 840.9200000000001,
      "end": 841.9200000000001,
      "speaker": "SPEAKER_03",
      "text": "Yo no la meto en el top 40, Uruguay."
    },
    {
      "start": 842.24,
      "end": 845.24,
      "speaker": "SPEAKER_03",
      "text": "Hombre, es estrictamente equivocado eso."
    },
    {
      "start": 845.24,
      "end": 850.24,
      "speaker": "SPEAKER_03",
      "text": "Bueno, si atendemos a la población que tiene las participaciones en el mundial, no entra"
    },
    {
      "start": 850.24,
      "end": 851.24,
      "speaker": "SPEAKER_03",
      "text": "en el top 40."
    },
    {
      "start": 851.24,
      "end": 852.24,
      "speaker": "SPEAKER_03",
      "text": "Entonces…"
    },
    {
      "start": 852.24,
      "end": 854.24,
      "speaker": "SPEAKER_03",
      "text": "No se le podría exigir a Uruguay que esté en el top 40."
    },
    {
      "start": 854.24,
      "end": 856.24,
      "speaker": "SPEAKER_03",
      "text": "Espera, que puede ir Surinam y Cabo Verde."
    },
    {
      "start": 856.24,
      "end": 857.24,
      "speaker": "SPEAKER_03",
      "text": "Vamos con el top 5."
    },
    {
      "start": 857.24,
      "end": 858.24,
      "speaker": "SPEAKER_00",
      "text": "A ver."
    },
    {
      "start": 858.24,
      "end": 859.24,
      "speaker": "SPEAKER_00",
      "text": "Yo creo que el top 5 es el potente de verdad."
    },
    {
      "start": 859.24,
      "end": 864.24,
      "speaker": "SPEAKER_00",
      "text": "Aquí ya veo un escalón de diferencia significativo que se puede acortar."
    },
    {
      "start": 864.24,
      "end": 867.24,
      "speaker": "SPEAKER_00",
      "text": "Pero hemos tenido claras las cinco primeras selecciones."
    },
    {
      "start": 867.24,
      "end": 870.24,
      "speaker": "SPEAKER_00",
      "text": "Yo había planteado un cambio de la selección de 2020."
    },
    {
      "start": 870.5600000000001,
      "end": 873.5600000000001,
      "speaker": "SPEAKER_00",
      "text": "Yo había planteado un cambio entre la quinta y la cuarta."
    },
    {
      "start": 873.5600000000001,
      "end": 875.5600000000001,
      "speaker": "SPEAKER_00",
      "text": "Al final no lo hemos hecho."
    },
    {
      "start": 875.5600000000001,
      "end": 877.5600000000001,
      "speaker": "SPEAKER_00",
      "text": "En quinta posición, Inglaterra."
    },
    {
      "start": 877.5600000000001,
      "end": 882.5600000000001,
      "speaker": "SPEAKER_00",
      "text": "Esa selección que todavía no ha dado el siguiente paso, esa selección que no es ganadora,"
    },
    {
      "start": 882.5600000000001,
      "end": 888.5600000000001,
      "speaker": "SPEAKER_00",
      "text": "no es ganadora, pero que está jugando bien, que tiene mucho talento, tiene un nuevo seleccionador"
    },
    {
      "start": 888.5600000000001,
      "end": 890.5600000000001,
      "speaker": "SPEAKER_00",
      "text": "que nos creemos mucho."
    },
    {
      "start": 890.5600000000001,
      "end": 893.5600000000001,
      "speaker": "SPEAKER_00",
      "text": "Yo a Inglaterra ahora mismo la situaría a cuarta."
    },
    {
      "start": 893.5600000000001,
      "end": 896.5600000000001,
      "speaker": "SPEAKER_02",
      "text": "Hay una cosa de tú, Gel, que me está gustando un poquito."
    },
    {
      "start": 896.5600000000001,
      "end": 898.5600000000001,
      "speaker": "SPEAKER_02",
      "text": "Que es, está sentando al equipo desde atrás."
    },
    {
      "start": 898.88,
      "end": 901.88,
      "speaker": "SPEAKER_02",
      "text": "Creo que es una cosa que a Inglaterra se le estaba resistiendo."
    },
    {
      "start": 901.88,
      "end": 904.88,
      "speaker": "SPEAKER_02",
      "text": "Inglaterra al final tiene potencial ofensivo a raudales."
    },
    {
      "start": 904.88,
      "end": 908.88,
      "speaker": "SPEAKER_02",
      "text": "Tiene a Harry Kane, a Bukayo Saka, a jugadores que le pueden solventar partidos."
    },
    {
      "start": 908.88,
      "end": 910.88,
      "speaker": "SPEAKER_02",
      "text": "Los que queráis."
    },
    {
      "start": 910.88,
      "end": 912.88,
      "speaker": "SPEAKER_02",
      "text": "Dos datines, si me dejas un momento."
    },
    {
      "start": 912.88,
      "end": 914.88,
      "speaker": "SPEAKER_02",
      "text": "Tomas tu gelabanado."
    },
    {
      "start": 914.88,
      "end": 916.88,
      "speaker": "SPEAKER_02",
      "text": "¿Te lo vas sentando desde atrás?"
    },
    {
      "start": 916.88,
      "end": 917.88,
      "speaker": "SPEAKER_02",
      "text": "¿Qué es decir?"
    },
    {
      "start": 917.88,
      "end": 918.88,
      "speaker": "SPEAKER_02",
      "text": "¿Saugrid también?"
    },
    {
      "start": 918.88,
      "end": 921.88,
      "speaker": "SPEAKER_00",
      "text": "El problema de Saugrid es que era un equipo rígido de narices."
    },
    {
      "start": 921.88,
      "end": 924.88,
      "speaker": "SPEAKER_02",
      "text": "Pero una cosa es construir desde atrás un equipo que sea fiable a nivel defensivo."
    },
    {
      "start": 924.88,
      "end": 927.88,
      "speaker": "SPEAKER_02",
      "text": "Y otra cosa es ser un equipo que parte desde atrás."
    },
    {
      "start": 928.2,
      "end": 931.2,
      "speaker": "SPEAKER_02",
      "text": "A mí no me parece que tú Gel esté partiendo desde atrás."
    },
    {
      "start": 931.2,
      "end": 933.2,
      "speaker": "SPEAKER_02",
      "text": "No veo la diferencia."
    },
    {
      "start": 933.2,
      "end": 935.2,
      "speaker": "SPEAKER_02",
      "text": "No veo la diferencia importante."
    },
    {
      "start": 935.2,
      "end": 938.2,
      "speaker": "SPEAKER_02",
      "text": "Tú puedes construir un equipo siendo encerrado."
    },
    {
      "start": 938.2,
      "end": 941.2,
      "speaker": "SPEAKER_02",
      "text": "Y otra cosa es un equipo que se comporte bien a nivel defensivo."
    },
    {
      "start": 941.2,
      "end": 943.2,
      "speaker": "SPEAKER_00",
      "text": "Y sea capaz de solver..."
    },
    {
      "start": 943.2,
      "end": 947.2,
      "speaker": "SPEAKER_02",
      "text": "Yo creo que la gran diferencia es que parte de una premisa parecía y tú Gel se va a hacer eso."
    },
    {
      "start": 947.2,
      "end": 949.2,
      "speaker": "SPEAKER_02",
      "text": "Puede ser. Puede estar ahí."
    },
    {
      "start": 949.2,
      "end": 952.2,
      "speaker": "SPEAKER_02",
      "text": "No ha encajado ningún gol tú Gel como seleccionador inglés."
    },
    {
      "start": 952.2,
      "end": 955.2,
      "speaker": "SPEAKER_02",
      "text": "Ese es el primer seleccionador inglés que en sus primeros cinco partidos los ha ganado todos."
    },
    {
      "start": 955.5200000000001,
      "end": 958.5200000000001,
      "speaker": "SPEAKER_02",
      "text": "Y además solo le han hecho un remate a puerta que fue Letonia."
    },
    {
      "start": 958.5200000000001,
      "end": 960.5200000000001,
      "speaker": "SPEAKER_02",
      "text": "En partidos oficiales."
    },
    {
      "start": 960.5200000000001,
      "end": 963.5200000000001,
      "speaker": "SPEAKER_02",
      "text": "Me refiero porque tienen ese amistoso antes Senegal que Palma."
    },
    {
      "start": 963.5200000000001,
      "end": 967.5200000000001,
      "speaker": "SPEAKER_02",
      "text": "Yo tengo dudas un poco de cómo es ese comportamiento ya en campo rival."
    },
    {
      "start": 967.5200000000001,
      "end": 969.5200000000001,
      "speaker": "SPEAKER_02",
      "text": "Todavía veo cosas..."
    },
    {
      "start": 969.5200000000001,
      "end": 971.5200000000001,
      "speaker": "SPEAKER_02",
      "text": "Todavía veo cosas que no..."
    },
    {
      "start": 971.5200000000001,
      "end": 974.5200000000001,
      "speaker": "SPEAKER_02",
      "text": "En medio de Andorra, por ejemplo, en Barcelona, que lo pude ver con mis ojos..."
    },
    {
      "start": 974.5200000000001,
      "end": 976.5200000000001,
      "speaker": "SPEAKER_02",
      "text": "Fue muy duro."
    },
    {
      "start": 976.5200000000001,
      "end": 979.5200000000001,
      "speaker": "SPEAKER_00",
      "text": "Para mí es la duda porque es lo que está por resolverse."
    },
    {
      "start": 979.5200000000001,
      "end": 982.5200000000001,
      "speaker": "SPEAKER_00",
      "text": "Lo que sí que es verdad es que tú Gel ha conseguido..."
    },
    {
      "start": 982.84,
      "end": 985.84,
      "speaker": "SPEAKER_00",
      "text": "Organizar equipos desde lo posicional muy positivo."
    },
    {
      "start": 985.84,
      "end": 987.84,
      "speaker": "SPEAKER_00",
      "text": "Tienen los futbolistas para eso."
    },
    {
      "start": 987.84,
      "end": 989.84,
      "speaker": "SPEAKER_00",
      "text": "Igual Inglaterra tiene otra cosa."
    },
    {
      "start": 989.84,
      "end": 992.84,
      "speaker": "SPEAKER_00",
      "text": "Pero lo de Sao Benz ya sí que parecía que estaba atascado."
    },
    {
      "start": 992.84,
      "end": 994.84,
      "speaker": "SPEAKER_00",
      "text": "Y mira que soy de los que valoro su trabajo."
    },
    {
      "start": 994.84,
      "end": 996.84,
      "speaker": "SPEAKER_00",
      "text": "Pero creo que el equipo para dar el siguiente nivel..."
    },
    {
      "start": 996.84,
      "end": 998.84,
      "speaker": "SPEAKER_00",
      "text": "Necesitaba un entrenador del siguiente nivel."
    },
    {
      "start": 998.84,
      "end": 1001.84,
      "speaker": "SPEAKER_01",
      "text": "Sí, también te digo que en torneos cortos de selecciones..."
    },
    {
      "start": 1001.84,
      "end": 1004.84,
      "speaker": "SPEAKER_01",
      "text": "Sabemos que funciona esto de llegar a una selección..."
    },
    {
      "start": 1004.84,
      "end": 1006.84,
      "speaker": "SPEAKER_01",
      "text": "Asumir poquitos riesgos."
    },
    {
      "start": 1006.84,
      "end": 1008.84,
      "speaker": "SPEAKER_01",
      "text": "De mínimos."
    },
    {
      "start": 1008.84,
      "end": 1010.84,
      "speaker": "SPEAKER_00",
      "text": "No encajar goles."
    },
    {
      "start": 1011.1600000000001,
      "end": 1013.1600000000001,
      "speaker": "SPEAKER_03",
      "text": "Entonces esto sí que funciona."
    },
    {
      "start": 1013.1600000000001,
      "end": 1015.1600000000001,
      "speaker": "SPEAKER_03",
      "text": "De Sao lleva 14 años."
    },
    {
      "start": 1015.1600000000001,
      "end": 1018.1600000000001,
      "speaker": "SPEAKER_01",
      "text": "Y tú Gel con algo más de margen, en otro contexto, lo hizo con su Chelsea."
    },
    {
      "start": 1018.1600000000001,
      "end": 1020.1600000000001,
      "speaker": "SPEAKER_01",
      "text": "Sí, pero es que es un poco su Chelsea."
    },
    {
      "start": 1020.1600000000001,
      "end": 1022.1600000000001,
      "speaker": "SPEAKER_00",
      "text": "O es un buenísimo error."
    },
    {
      "start": 1022.1600000000001,
      "end": 1025.16,
      "speaker": "SPEAKER_00",
      "text": "Pero mi duda es que yo veo a los de arriba de Inglaterra..."
    },
    {
      "start": 1025.16,
      "end": 1030.16,
      "speaker": "SPEAKER_00",
      "text": "Y no veo ni la velocidad y autosuficiencia de Francia..."
    },
    {
      "start": 1030.16,
      "end": 1032.16,
      "speaker": "SPEAKER_00",
      "text": "Que citabais desde Sao Benz."
    },
    {
      "start": 1032.16,
      "end": 1035.16,
      "speaker": "SPEAKER_00",
      "text": "Ni al perfil de futbolista que tenía ese Chelsea."
    },
    {
      "start": 1035.16,
      "end": 1038.16,
      "speaker": "SPEAKER_00",
      "text": "Veo un equipo que agradecería juntarse en torno a la pelota..."
    },
    {
      "start": 1038.48,
      "end": 1040.48,
      "speaker": "SPEAKER_00",
      "text": "Y con tanta rigidez y inflexibilidad."
    },
    {
      "start": 1040.48,
      "end": 1042.48,
      "speaker": "SPEAKER_00",
      "text": "Que es lo que caracterizaba Sao."
    },
    {
      "start": 1042.48,
      "end": 1044.48,
      "speaker": "SPEAKER_03",
      "text": "Acordas de Foden pegadas a la banda izquierda."
    },
    {
      "start": 1044.48,
      "end": 1047.48,
      "speaker": "SPEAKER_03",
      "text": "Le habría encantado a ese Chelsea contar con Noni Madueke..."
    },
    {
      "start": 1047.48,
      "end": 1049.48,
      "speaker": "SPEAKER_03",
      "text": "Que es, según los compañeros de Okta..."
    },
    {
      "start": 1049.48,
      "end": 1054.48,
      "speaker": "SPEAKER_03",
      "text": "El primer futbolista de la selección Inglaterra desde el año 97..."
    },
    {
      "start": 1054.48,
      "end": 1057.48,
      "speaker": "SPEAKER_03",
      "text": "En marcar y tener en su nombre todas las vocales."
    },
    {
      "start": 1057.48,
      "end": 1060.48,
      "speaker": "SPEAKER_02",
      "text": "Y fue su primer gol con Inglaterra, por cierto."
    },
    {
      "start": 1060.48,
      "end": 1062.48,
      "speaker": "SPEAKER_02",
      "text": "Y una cosa, simplemente."
    },
    {
      "start": 1062.48,
      "end": 1066.48,
      "speaker": "SPEAKER_02",
      "text": "Albania, Letonia, Andorra y Serbia han sido los rivales de la Inglaterra de tú Gel."
    },
    {
      "start": 1066.8,
      "end": 1068.8,
      "speaker": "SPEAKER_02",
      "text": "Nivel medio superior a Sudamérica."
    },
    {
      "start": 1068.8,
      "end": 1070.8,
      "speaker": "SPEAKER_02",
      "text": "Hay que tenerlo también en cuenta."
    },
    {
      "start": 1070.8,
      "end": 1073.8,
      "speaker": "SPEAKER_00",
      "text": "Bolivia está prácticamente clasificada perdiendo de partido."
    },
    {
      "start": 1073.8,
      "end": 1075.8,
      "speaker": "SPEAKER_00",
      "text": "Prácticamente."
    },
    {
      "start": 1075.8,
      "end": 1077.8,
      "speaker": "SPEAKER_00",
      "text": "Cuarta clasificada en nuestro powerrank en aquén."
    },
    {
      "start": 1077.8,
      "end": 1079.8,
      "speaker": "SPEAKER_00",
      "text": "Yo pondría quien, te insisto."
    },
    {
      "start": 1079.8,
      "end": 1081.8,
      "speaker": "SPEAKER_00",
      "text": "Francia."
    },
    {
      "start": 1081.8,
      "end": 1083.8,
      "speaker": "SPEAKER_00",
      "text": "Talento ya lo sabemos."
    },
    {
      "start": 1083.8,
      "end": 1085.8,
      "speaker": "SPEAKER_00",
      "text": "Y siempre está ahí y hay que ganarla."
    },
    {
      "start": 1085.8,
      "end": 1087.8,
      "speaker": "SPEAKER_00",
      "text": "Y nos costó en semifinal de Eurocopa."
    },
    {
      "start": 1087.8,
      "end": 1091.8,
      "speaker": "SPEAKER_00",
      "text": "Pero ver los partidos y todavía..."
    },
    {
      "start": 1091.8,
      "end": 1093.8,
      "speaker": "SPEAKER_00",
      "text": "No sé."
    },
    {
      "start": 1093.8,
      "end": 1095.8,
      "speaker": "SPEAKER_00",
      "text": "A mí el de Ucrania me gustó."
    },
    {
      "start": 1096.12,
      "end": 1098.12,
      "speaker": "SPEAKER_00",
      "text": "Es que el de Islandia..."
    },
    {
      "start": 1098.12,
      "end": 1101.12,
      "speaker": "SPEAKER_03",
      "text": "Ucrania que posteriormente ha empatado a uno contra la Zerbaian."
    },
    {
      "start": 1101.12,
      "end": 1104.12,
      "speaker": "SPEAKER_01",
      "text": "Bueno, pero hay que medir a los rivales."
    },
    {
      "start": 1104.12,
      "end": 1106.12,
      "speaker": "SPEAKER_01",
      "text": "No me puedo inventar el partido."
    },
    {
      "start": 1106.12,
      "end": 1108.12,
      "speaker": "SPEAKER_01",
      "text": "Pero me gustó."
    },
    {
      "start": 1108.12,
      "end": 1110.12,
      "speaker": "SPEAKER_01",
      "text": "La primera parte de Francia me gustó."
    },
    {
      "start": 1110.12,
      "end": 1112.12,
      "speaker": "SPEAKER_01",
      "text": "Yendo arriba, teniendo la pelota."
    },
    {
      "start": 1112.12,
      "end": 1114.12,
      "speaker": "SPEAKER_00",
      "text": "A mí el conecho a Mení..."
    },
    {
      "start": 1114.12,
      "end": 1116.12,
      "speaker": "SPEAKER_00",
      "text": "Conecho a Mení suena a Pogba Kante."
    },
    {
      "start": 1116.12,
      "end": 1120.12,
      "speaker": "SPEAKER_00",
      "text": "Es verdad que contra Islandia no puede contar con Dembelen y con Douai."
    },
    {
      "start": 1120.12,
      "end": 1122.12,
      "speaker": "SPEAKER_00",
      "text": "Eso es verdad."
    },
    {
      "start": 1122.12,
      "end": 1124.12,
      "speaker": "SPEAKER_00",
      "text": "Le sobra polvo arriba, en Bapesta, finísimo."
    },
    {
      "start": 1124.4399999999998,
      "end": 1128.4399999999998,
      "speaker": "SPEAKER_02",
      "text": "En las descargas, en los apoyos, en los dos marques..."
    },
    {
      "start": 1128.4399999999998,
      "end": 1131.4399999999998,
      "speaker": "SPEAKER_00",
      "text": "El tema es ver si con eso le va a dar."
    },
    {
      "start": 1131.4399999999998,
      "end": 1135.4399999999998,
      "speaker": "SPEAKER_00",
      "text": "Francia, Nahuel, parece una foto fija."
    },
    {
      "start": 1135.4399999999998,
      "end": 1138.4399999999998,
      "speaker": "SPEAKER_00",
      "text": "Cambian a algunos futbolistas, evolucionan otros tantos."
    },
    {
      "start": 1138.4399999999998,
      "end": 1140.4399999999998,
      "speaker": "SPEAKER_00",
      "text": "Cambian a los rivales."
    },
    {
      "start": 1140.4399999999998,
      "end": 1142.4399999999998,
      "speaker": "SPEAKER_00",
      "text": "Pero la Francia de Samp sigue ahí."
    },
    {
      "start": 1142.4399999999998,
      "end": 1144.4399999999998,
      "speaker": "SPEAKER_00",
      "text": "En lo positivo y en lo no tan positivo."
    },
    {
      "start": 1144.4399999999998,
      "end": 1148.4399999999998,
      "speaker": "SPEAKER_03",
      "text": "Es cierto que a raíz de la crítica que hace Samp"
    },
    {
      "start": 1148.4399999999998,
      "end": 1151.4399999999998,
      "speaker": "SPEAKER_03",
      "text": "contra sus propios jugadores después de la final del 22,"
    },
    {
      "start": 1151.76,
      "end": 1153.76,
      "speaker": "SPEAKER_03",
      "text": "70 minutos de partido."
    },
    {
      "start": 1153.76,
      "end": 1155.76,
      "speaker": "SPEAKER_03",
      "text": "Hay 7 o 8 que los habría cambiado."
    },
    {
      "start": 1155.76,
      "end": 1157.76,
      "speaker": "SPEAKER_03",
      "text": "Creo que se han puesto..."
    },
    {
      "start": 1157.76,
      "end": 1159.76,
      "speaker": "SPEAKER_03",
      "text": "Las peores finales disputadas al menos de inicio."
    },
    {
      "start": 1159.76,
      "end": 1162.76,
      "speaker": "SPEAKER_03",
      "text": "Luego aparece Mbappé y cambia un poquito la historia."
    },
    {
      "start": 1162.76,
      "end": 1164.76,
      "speaker": "SPEAKER_03",
      "text": "Se ha girado un poquito el disparo."
    },
    {
      "start": 1164.76,
      "end": 1168.76,
      "speaker": "SPEAKER_03",
      "text": "Había mucho miedo al relevo de Griezmann, que hace un mundial tremendo."
    },
    {
      "start": 1168.76,
      "end": 1170.76,
      "speaker": "SPEAKER_03",
      "text": "Creo que ese problema lo ha solventado."
    },
    {
      "start": 1170.76,
      "end": 1172.76,
      "speaker": "SPEAKER_03",
      "text": "Con Olise."
    },
    {
      "start": 1172.76,
      "end": 1174.76,
      "speaker": "SPEAKER_03",
      "text": "Yo creo que sí."
    },
    {
      "start": 1174.76,
      "end": 1176.76,
      "speaker": "SPEAKER_03",
      "text": "Es buenísimo."
    },
    {
      "start": 1176.76,
      "end": 1178.76,
      "speaker": "SPEAKER_00",
      "text": "Pero que no reciba dentro del área."
    },
    {
      "start": 1178.76,
      "end": 1180.76,
      "speaker": "SPEAKER_03",
      "text": "El lío del otro día."
    },
    {
      "start": 1181.08,
      "end": 1185.08,
      "speaker": "SPEAKER_03",
      "text": "Hay muchos futbolistas jóvenes que tomaron el relevo de la generación que gana el 18."
    },
    {
      "start": 1185.08,
      "end": 1187.08,
      "speaker": "SPEAKER_03",
      "text": "Que están en un momento de plenitud."
    },
    {
      "start": 1187.08,
      "end": 1189.08,
      "speaker": "SPEAKER_03",
      "text": "Y yo quiero ver el caso de Dembele."
    },
    {
      "start": 1189.08,
      "end": 1192.08,
      "speaker": "SPEAKER_03",
      "text": "A ver si vemos un Dembele parecido al de la temporada pasada del PSG."
    },
    {
      "start": 1192.08,
      "end": 1194.08,
      "speaker": "SPEAKER_00",
      "text": "En tercera posición."
    },
    {
      "start": 1194.08,
      "end": 1196.08,
      "speaker": "SPEAKER_00",
      "text": "Hemos situado."
    },
    {
      "start": 1196.08,
      "end": 1198.08,
      "speaker": "SPEAKER_00",
      "text": "Y aquí la cosa se pone seria."
    },
    {
      "start": 1198.08,
      "end": 1201.08,
      "speaker": "SPEAKER_00",
      "text": "Yo creo que este top 5 más o menos lo daba todo el mundo."
    },
    {
      "start": 1201.08,
      "end": 1203.08,
      "speaker": "SPEAKER_00",
      "text": "Las 5 secciones, digo."
    },
    {
      "start": 1203.08,
      "end": 1205.08,
      "speaker": "SPEAKER_02",
      "text": "No el orden."
    },
    {
      "start": 1205.08,
      "end": 1207.08,
      "speaker": "SPEAKER_02",
      "text": "Yo creo que es un top 5 en el que hay un escalón."
    },
    {
      "start": 1207.08,
      "end": 1209.08,
      "speaker": "SPEAKER_02",
      "text": "Por encima de las otras tres."
    },
    {
      "start": 1209.3999999999999,
      "end": 1211.3999999999999,
      "speaker": "SPEAKER_00",
      "text": "Pero si tú has el escalón entre el cuarto y el tercero."
    },
    {
      "start": 1211.3999999999999,
      "end": 1213.3999999999999,
      "speaker": "SPEAKER_02",
      "text": "Entre el segundo y el tercero."
    },
    {
      "start": 1213.3999999999999,
      "end": 1215.3999999999999,
      "speaker": "SPEAKER_02",
      "text": "Claro."
    },
    {
      "start": 1215.3999999999999,
      "end": 1217.3999999999999,
      "speaker": "SPEAKER_00",
      "text": "Es que yo lo sitúo entre el tercero y el cuarto."
    },
    {
      "start": 1217.3999999999999,
      "end": 1219.3999999999999,
      "speaker": "SPEAKER_02",
      "text": "¿Ah, sí?"
    },
    {
      "start": 1219.3999999999999,
      "end": 1221.3999999999999,
      "speaker": "SPEAKER_03",
      "text": "Tú has hecho la del robot que diseña Lisa."
    },
    {
      "start": 1221.3999999999999,
      "end": 1223.3999999999999,
      "speaker": "SPEAKER_03",
      "text": "Sí."
    },
    {
      "start": 1223.3999999999999,
      "end": 1225.3999999999999,
      "speaker": "SPEAKER_03",
      "text": "El episodio de las vidas paralelas de los Simpsons."
    },
    {
      "start": 1225.3999999999999,
      "end": 1227.3999999999999,
      "speaker": "SPEAKER_00",
      "text": "Yo sitúo a Portugal tercera."
    },
    {
      "start": 1227.3999999999999,
      "end": 1229.3999999999999,
      "speaker": "SPEAKER_00",
      "text": "Vamos, lo situamos."
    },
    {
      "start": 1229.3999999999999,
      "end": 1231.3999999999999,
      "speaker": "SPEAKER_00",
      "text": "Y para mí Portugal."
    },
    {
      "start": 1231.3999999999999,
      "end": 1233.3999999999999,
      "speaker": "SPEAKER_00",
      "text": "Ahora mismo está un poquito más cerquita."
    },
    {
      "start": 1233.3999999999999,
      "end": 1235.3999999999999,
      "speaker": "SPEAKER_00",
      "text": "De las dos que nos quedan que de las dos por detrás."
    },
    {
      "start": 1235.3999999999999,
      "end": 1237.3999999999999,
      "speaker": "SPEAKER_00",
      "text": "Igual tiene su escalón propio."
    },
    {
      "start": 1237.72,
      "end": 1239.72,
      "speaker": "SPEAKER_00",
      "text": "Pero yo por eso sitúo a la diferencia ahí."
    },
    {
      "start": 1239.72,
      "end": 1241.72,
      "speaker": "SPEAKER_01",
      "text": "Yo le daría quizás un escalón."
    },
    {
      "start": 1241.72,
      "end": 1243.72,
      "speaker": "SPEAKER_01",
      "text": "Pero no le metería aún."
    },
    {
      "start": 1243.72,
      "end": 1245.72,
      "speaker": "SPEAKER_01",
      "text": "En el de las dos primeras que vamos a destacar ahora."
    },
    {
      "start": 1245.72,
      "end": 1247.72,
      "speaker": "SPEAKER_00",
      "text": "¿Ves potencial para que suba?"
    },
    {
      "start": 1247.72,
      "end": 1249.72,
      "speaker": "SPEAKER_00",
      "text": "Porque hay muchos jugadores que están llegando muy muy bien."
    },
    {
      "start": 1249.72,
      "end": 1251.72,
      "speaker": "SPEAKER_00",
      "text": "Una base competitiva top."
    },
    {
      "start": 1251.72,
      "end": 1253.72,
      "speaker": "SPEAKER_00",
      "text": "El partido que nos planteó en la Nations."
    },
    {
      "start": 1253.72,
      "end": 1255.72,
      "speaker": "SPEAKER_00",
      "text": "Creo que fue soberbio."
    },
    {
      "start": 1255.72,
      "end": 1257.72,
      "speaker": "SPEAKER_01",
      "text": "Creo que ha crecido como selección."
    },
    {
      "start": 1257.72,
      "end": 1259.72,
      "speaker": "SPEAKER_01",
      "text": "En cuanto al propio juego ha evolucionado."
    },
    {
      "start": 1259.72,
      "end": 1261.72,
      "speaker": "SPEAKER_01",
      "text": "Porque con Roberto Martínez los primeros partidos fueron"
    },
    {
      "start": 1261.72,
      "end": 1263.72,
      "speaker": "SPEAKER_01",
      "text": "de un ataque posicional bastante atascado."
    },
    {
      "start": 1263.72,
      "end": 1265.72,
      "speaker": "SPEAKER_01",
      "text": "Que le costaba bastante a Portugal."
    },
    {
      "start": 1266.04,
      "end": 1268.04,
      "speaker": "SPEAKER_01",
      "text": "Y creo que ha sido para preparar este continuo del partido ante Armenia."
    },
    {
      "start": 1268.04,
      "end": 1270.04,
      "speaker": "SPEAKER_01",
      "text": "Siendo la selección de Armenia."
    },
    {
      "start": 1270.04,
      "end": 1272.04,
      "speaker": "SPEAKER_01",
      "text": "Perfectamente hay que contextualizarlo."
    },
    {
      "start": 1272.04,
      "end": 1274.04,
      "speaker": "SPEAKER_01",
      "text": "Pero el ataque posicional me pareció bastante interesante."
    },
    {
      "start": 1274.04,
      "end": 1276.04,
      "speaker": "SPEAKER_01",
      "text": "Creo que es una selección que ha ganado recursos."
    },
    {
      "start": 1276.04,
      "end": 1278.04,
      "speaker": "SPEAKER_01",
      "text": "Y que como dices tiene a varios futbolistas que son de los mejores del mundo."
    },
    {
      "start": 1278.04,
      "end": 1280.04,
      "speaker": "SPEAKER_01",
      "text": "Y Vitinha parte muy atrás."
    },
    {
      "start": 1280.04,
      "end": 1282.04,
      "speaker": "SPEAKER_01",
      "text": "Desde muy abajo."
    },
    {
      "start": 1282.04,
      "end": 1284.04,
      "speaker": "SPEAKER_02",
      "text": "Y Joan de Villers muy arriba."
    },
    {
      "start": 1284.04,
      "end": 1286.04,
      "speaker": "SPEAKER_02",
      "text": "Están muy divididos."
    },
    {
      "start": 1286.04,
      "end": 1288.04,
      "speaker": "SPEAKER_02",
      "text": "Yo creo que tiene el aval de haber ganado la Nations."
    },
    {
      "start": 1288.04,
      "end": 1290.04,
      "speaker": "SPEAKER_02",
      "text": "De habernos complicado tanto."
    },
    {
      "start": 1290.04,
      "end": 1292.04,
      "speaker": "SPEAKER_02",
      "text": "De tener buenos resultados en esta fase de clasificación."
    },
    {
      "start": 1292.04,
      "end": 1294.04,
      "speaker": "SPEAKER_02",
      "text": "No es selección mundialista."
    },
    {
      "start": 1294.36,
      "end": 1296.36,
      "speaker": "SPEAKER_02",
      "text": "Claro, justo. Es que en fases finales no me lo he terminado a creer."
    },
    {
      "start": 1296.36,
      "end": 1298.36,
      "speaker": "SPEAKER_02",
      "text": "No terminé a cuajarme."
    },
    {
      "start": 1298.36,
      "end": 1300.36,
      "speaker": "SPEAKER_03",
      "text": "¿Dudas con la pareja de centales?"
    },
    {
      "start": 1300.36,
      "end": 1302.36,
      "speaker": "SPEAKER_03",
      "text": "Sí."
    },
    {
      "start": 1302.36,
      "end": 1304.36,
      "speaker": "SPEAKER_03",
      "text": "Y mucha contribución de los jugadores que están en Arabia."
    },
    {
      "start": 1304.36,
      "end": 1306.36,
      "speaker": "SPEAKER_03",
      "text": "Todavía."
    },
    {
      "start": 1306.36,
      "end": 1308.36,
      "speaker": "SPEAKER_03",
      "text": "Lo hablábamos con Rubio en la primera hora."
    },
    {
      "start": 1308.36,
      "end": 1310.36,
      "speaker": "SPEAKER_03",
      "text": "A ver, a mí me convence bastante."
    },
    {
      "start": 1310.36,
      "end": 1312.36,
      "speaker": "SPEAKER_00",
      "text": "¿Tú qué le pondrías? ¿Más cerca de las dos que nos quedan?"
    },
    {
      "start": 1312.36,
      "end": 1314.36,
      "speaker": "SPEAKER_03",
      "text": "O más cerca de las dos por detrás?"
    },
    {
      "start": 1314.36,
      "end": 1316.36,
      "speaker": "SPEAKER_03",
      "text": "Más cerca de las dos de arriba."
    },
    {
      "start": 1316.36,
      "end": 1318.36,
      "speaker": "SPEAKER_00",
      "text": "Vale. Las dos de arriba."
    },
    {
      "start": 1318.36,
      "end": 1320.36,
      "speaker": "SPEAKER_00",
      "text": "Os imagináis cuáles son."
    },
    {
      "start": 1320.36,
      "end": 1322.36,
      "speaker": "SPEAKER_00",
      "text": "Son Argentina y España. España y Argentina."
    },
    {
      "start": 1322.6799999999998,
      "end": 1324.6799999999998,
      "speaker": "SPEAKER_00",
      "text": "¿El orden?"
    },
    {
      "start": 1324.6799999999998,
      "end": 1326.6799999999998,
      "speaker": "SPEAKER_00",
      "text": "¿Lo hemos decidido de forma unánime?"
    },
    {
      "start": 1326.6799999999998,
      "end": 1328.6799999999998,
      "speaker": "SPEAKER_00",
      "text": "¿Estamos de acuerdo a los cuatro?"
    },
    {
      "start": 1328.6799999999998,
      "end": 1330.6799999999998,
      "speaker": "SPEAKER_02",
      "text": "Yo creo que ahora mismo no."
    },
    {
      "start": 1330.6799999999998,
      "end": 1334.6799999999998,
      "speaker": "SPEAKER_02",
      "text": "Yo ahora mismo me pido el cuerpo poner a otra por delante del lado."
    },
    {
      "start": 1334.6799999999998,
      "end": 1336.6799999999998,
      "speaker": "SPEAKER_02",
      "text": "No."
    },
    {
      "start": 1336.6799999999998,
      "end": 1338.6799999999998,
      "speaker": "SPEAKER_00",
      "text": "A mí me pide sorpaso también. Yo tengo dudas."
    },
    {
      "start": 1338.6799999999998,
      "end": 1340.6799999999998,
      "speaker": "SPEAKER_00",
      "text": "Lo podíais haber dicho cuando lo he preguntado."
    },
    {
      "start": 1340.6799999999998,
      "end": 1342.6799999999998,
      "speaker": "SPEAKER_00",
      "text": "Bueno, hombre."
    },
    {
      "start": 1342.6799999999998,
      "end": 1344.6799999999998,
      "speaker": "SPEAKER_00",
      "text": "Pero si lo bueno es debatirlo."
    },
    {
      "start": 1344.6799999999998,
      "end": 1346.6799999999998,
      "speaker": "SPEAKER_00",
      "text": "No, lo podéis decir."
    },
    {
      "start": 1346.6799999999998,
      "end": 1348.6799999999998,
      "speaker": "SPEAKER_00",
      "text": "Porque luego decimos que el powerrank tiene 4 y me encuentro que no."
    },
    {
      "start": 1348.6799999999998,
      "end": 1350.6799999999998,
      "speaker": "SPEAKER_00",
      "text": "Es debate."
    },
    {
      "start": 1351.0,
      "end": 1353.0,
      "speaker": "SPEAKER_00",
      "text": "En segunda posición."
    },
    {
      "start": 1353.0,
      "end": 1355.0,
      "speaker": "SPEAKER_00",
      "text": "¿Hemos colocado?"
    },
    {
      "start": 1355.0,
      "end": 1357.0,
      "speaker": "SPEAKER_00",
      "text": "¿Hemos? En plural."
    },
    {
      "start": 1357.0,
      "end": 1359.0,
      "speaker": "SPEAKER_00",
      "text": "¿A España? ¿A la selección española?"
    },
    {
      "start": 1359.0,
      "end": 1361.0,
      "speaker": "SPEAKER_00",
      "text": "No."
    },
    {
      "start": 1361.0,
      "end": 1363.0,
      "speaker": "SPEAKER_00",
      "text": "Yo creo que no encuentro motivo."
    },
    {
      "start": 1363.0,
      "end": 1365.0,
      "speaker": "SPEAKER_00",
      "text": "Y decimos ya quién es la primera"
    },
    {
      "start": 1365.0,
      "end": 1367.0,
      "speaker": "SPEAKER_00",
      "text": "clasificada."
    },
    {
      "start": 1367.0,
      "end": 1369.0,
      "speaker": "SPEAKER_00",
      "text": "Nuestra primera favorita."
    },
    {
      "start": 1369.0,
      "end": 1371.0,
      "speaker": "SPEAKER_00",
      "text": "En este primer powerranking que es Argentina evidentemente."
    },
    {
      "start": 1371.0,
      "end": 1373.0,
      "speaker": "SPEAKER_00",
      "text": "Yo no veo motivo para bajar Argentina."
    },
    {
      "start": 1373.0,
      "end": 1375.0,
      "speaker": "SPEAKER_00",
      "text": "Veo motivos para subir a España."
    },
    {
      "start": 1375.0,
      "end": 1377.0,
      "speaker": "SPEAKER_00",
      "text": "Lo que no veo es motivo para bajar Argentina."
    },
    {
      "start": 1377.0,
      "end": 1379.0,
      "speaker": "SPEAKER_00",
      "text": "Me pasa como con el Liverpool y el Paris Saint Germain."
    },
    {
      "start": 1379.32,
      "end": 1381.32,
      "speaker": "SPEAKER_00",
      "text": "Yo diría que el máximo favorito es el Paris Saint Germain."
    },
    {
      "start": 1381.32,
      "end": 1383.32,
      "speaker": "SPEAKER_00",
      "text": "Pero el Liverpool ha crecido en la realidad."
    },
    {
      "start": 1383.32,
      "end": 1385.32,
      "speaker": "SPEAKER_00",
      "text": "Pero el Paris Saint Germain no veo..."
    },
    {
      "start": 1385.32,
      "end": 1387.32,
      "speaker": "SPEAKER_00",
      "text": "No debería caer."
    },
    {
      "start": 1387.32,
      "end": 1389.32,
      "speaker": "SPEAKER_00",
      "text": "No."
    },
    {
      "start": 1389.32,
      "end": 1391.32,
      "speaker": "SPEAKER_02",
      "text": "España está en la segunda mejor racha de su historia."
    },
    {
      "start": 1391.32,
      "end": 1393.32,
      "speaker": "SPEAKER_02",
      "text": "Estamos viendo un fútbol"
    },
    {
      "start": 1393.32,
      "end": 1395.32,
      "speaker": "SPEAKER_02",
      "text": "super atractivo."
    },
    {
      "start": 1395.32,
      "end": 1397.32,
      "speaker": "SPEAKER_02",
      "text": "Están vendiendo los resultados."
    },
    {
      "start": 1397.32,
      "end": 1399.32,
      "speaker": "SPEAKER_02",
      "text": "Campeona de la Eurocopa."
    },
    {
      "start": 1399.32,
      "end": 1401.32,
      "speaker": "SPEAKER_02",
      "text": "La Minyamal volando."
    },
    {
      "start": 1401.32,
      "end": 1403.32,
      "speaker": "SPEAKER_02",
      "text": "Una selección que en conjunto y en individual está destacando."
    },
    {
      "start": 1403.32,
      "end": 1405.32,
      "speaker": "SPEAKER_02",
      "text": "Y falta ese paso del Mundial."
    },
    {
      "start": 1405.32,
      "end": 1407.32,
      "speaker": "SPEAKER_02",
      "text": "Argentina ya la ha dado."
    },
    {
      "start": 1407.6399999999999,
      "end": 1409.6399999999999,
      "speaker": "SPEAKER_02",
      "text": "Tiene una selección que se experta."
    },
    {
      "start": 1409.6399999999999,
      "end": 1411.6399999999999,
      "speaker": "SPEAKER_02",
      "text": "O que ya ha sido capaz de tocar ese metal."
    },
    {
      "start": 1411.6399999999999,
      "end": 1413.6399999999999,
      "speaker": "SPEAKER_02",
      "text": "Yo sí que estoy viendo una selección de Argentina."
    },
    {
      "start": 1413.6399999999999,
      "end": 1415.6399999999999,
      "speaker": "SPEAKER_02",
      "text": "Igual en estos duelos contra España."
    },
    {
      "start": 1415.6399999999999,
      "end": 1417.6399999999999,
      "speaker": "SPEAKER_02",
      "text": "Alemania."
    },
    {
      "start": 1417.6399999999999,
      "end": 1419.6399999999999,
      "speaker": "SPEAKER_02",
      "text": "Alemania es un mal ejemplo. Francia."
    },
    {
      "start": 1419.6399999999999,
      "end": 1421.6399999999999,
      "speaker": "SPEAKER_02",
      "text": "Quiero verla."
    },
    {
      "start": 1421.6399999999999,
      "end": 1423.6399999999999,
      "speaker": "SPEAKER_02",
      "text": "Porque creo que ha bajado un poco respecto al 22."
    },
    {
      "start": 1423.6399999999999,
      "end": 1425.6399999999999,
      "speaker": "SPEAKER_01",
      "text": "Son dos selecciones que juegan de memoria."
    },
    {
      "start": 1425.6399999999999,
      "end": 1427.6399999999999,
      "speaker": "SPEAKER_01",
      "text": "Dos equipos."
    },
    {
      "start": 1427.6399999999999,
      "end": 1429.6399999999999,
      "speaker": "SPEAKER_01",
      "text": "Son dos equipazos con dos entrenadores."
    },
    {
      "start": 1429.6399999999999,
      "end": 1431.6399999999999,
      "speaker": "SPEAKER_01",
      "text": "Dos seleccionadores que están optimizando al máximo el talento."
    },
    {
      "start": 1431.6399999999999,
      "end": 1433.6399999999999,
      "speaker": "SPEAKER_01",
      "text": "La duda que tengo con Argentina"
    },
    {
      "start": 1433.6399999999999,
      "end": 1435.6399999999999,
      "speaker": "SPEAKER_01",
      "text": "de cara al Mundial."
    },
    {
      "start": 1435.96,
      "end": 1437.96,
      "speaker": "SPEAKER_01",
      "text": "En Qatar es la cuestión emocional."
    },
    {
      "start": 1437.96,
      "end": 1439.96,
      "speaker": "SPEAKER_01",
      "text": "Es el tema emocional con Messi."
    },
    {
      "start": 1439.96,
      "end": 1441.96,
      "speaker": "SPEAKER_01",
      "text": "Otra vez."
    },
    {
      "start": 1441.96,
      "end": 1443.96,
      "speaker": "SPEAKER_00",
      "text": "Escaloni."
    },
    {
      "start": 1443.96,
      "end": 1445.96,
      "speaker": "SPEAKER_00",
      "text": "Yo te diría que ese es un check más que hecho."
    },
    {
      "start": 1445.96,
      "end": 1447.96,
      "speaker": "SPEAKER_00",
      "text": "Entre las Copas Américas."
    },
    {
      "start": 1447.96,
      "end": 1449.96,
      "speaker": "SPEAKER_01",
      "text": "El Mundial."
    },
    {
      "start": 1449.96,
      "end": 1451.96,
      "speaker": "SPEAKER_01",
      "text": "El otro día juega Messi su última parte en Argentina."
    },
    {
      "start": 1451.96,
      "end": 1453.96,
      "speaker": "SPEAKER_00",
      "text": "Y Escaloni vuelve a llorar."
    },
    {
      "start": 1453.96,
      "end": 1455.96,
      "speaker": "SPEAKER_00",
      "text": "Y se pasean."
    },
    {
      "start": 1455.96,
      "end": 1457.96,
      "speaker": "SPEAKER_00",
      "text": "Y yo creo que Argentina siempre va a tener ese punto emocional."
    },
    {
      "start": 1457.96,
      "end": 1459.96,
      "speaker": "SPEAKER_00",
      "text": "No es Europa."
    },
    {
      "start": 1459.96,
      "end": 1461.96,
      "speaker": "SPEAKER_01",
      "text": "Pero ese punto emocional"
    },
    {
      "start": 1461.96,
      "end": 1463.96,
      "speaker": "SPEAKER_01",
      "text": "la has leído muy bien o muy mal."
    },
    {
      "start": 1464.28,
      "end": 1466.28,
      "speaker": "SPEAKER_01",
      "text": "El mismo está remando a favor."
    },
    {
      "start": 1466.28,
      "end": 1468.28,
      "speaker": "SPEAKER_02",
      "text": "En 2018..."
    },
    {
      "start": 1468.28,
      "end": 1470.28,
      "speaker": "SPEAKER_02",
      "text": "Era una contra y ahora lo veo una virtud."
    },
    {
      "start": 1470.28,
      "end": 1472.28,
      "speaker": "SPEAKER_02",
      "text": "Fíjate la actitud de Messi con el himno."
    },
    {
      "start": 1472.28,
      "end": 1474.28,
      "speaker": "SPEAKER_02",
      "text": "Antes se tapaba. Incluso ponía la cara."
    },
    {
      "start": 1474.28,
      "end": 1476.28,
      "speaker": "SPEAKER_00",
      "text": "Y ahora lo canta."
    },
    {
      "start": 1476.28,
      "end": 1478.28,
      "speaker": "SPEAKER_00",
      "text": "Dicho lo cual, con España no hace falta motivos para poner la prima."
    },
    {
      "start": 1478.28,
      "end": 1480.28,
      "speaker": "SPEAKER_00",
      "text": "Hay de sobra."
    },
    {
      "start": 1480.28,
      "end": 1482.28,
      "speaker": "SPEAKER_00",
      "text": "Quizás el único punto es que hay que ver"
    },
    {
      "start": 1482.28,
      "end": 1484.28,
      "speaker": "SPEAKER_00",
      "text": "cómo llegan Rodri y Carvajal."
    },
    {
      "start": 1484.28,
      "end": 1486.28,
      "speaker": "SPEAKER_00",
      "text": "Porque Rodri y Carvajal ya tienen el alta..."
    },
    {
      "start": 1486.28,
      "end": 1488.28,
      "speaker": "SPEAKER_00",
      "text": "Como tú lo decías antes con Musiala."
    },
    {
      "start": 1488.28,
      "end": 1490.28,
      "speaker": "SPEAKER_00",
      "text": "El alta..."
    },
    {
      "start": 1490.28,
      "end": 1492.28,
      "speaker": "SPEAKER_00",
      "text": "Médica."
    },
    {
      "start": 1492.6,
      "end": 1494.6,
      "speaker": "SPEAKER_00",
      "text": "Y para situar por delante de Argentina"
    },
    {
      "start": 1494.6,
      "end": 1496.6,
      "speaker": "SPEAKER_00",
      "text": "necesito una versión de Rodri y Carvajal."
    },
    {
      "start": 1496.6,
      "end": 1498.6,
      "speaker": "SPEAKER_00",
      "text": "No sé si la de la Eurocopa."
    },
    {
      "start": 1498.6,
      "end": 1500.6,
      "speaker": "SPEAKER_00",
      "text": "Quizás la mejor temporada de los dos."
    },
    {
      "start": 1500.6,
      "end": 1502.6,
      "speaker": "SPEAKER_00",
      "text": "Uno a caballón de oro."
    },
    {
      "start": 1502.6,
      "end": 1504.6,
      "speaker": "SPEAKER_00",
      "text": "El otro cuarto o quinto."
    },
    {
      "start": 1504.6,
      "end": 1506.6,
      "speaker": "SPEAKER_00",
      "text": "No sé si eso."
    },
    {
      "start": 1506.6,
      "end": 1508.6,
      "speaker": "SPEAKER_00",
      "text": "Pero algo cercano a eso sí que necesitaría."
    },
    {
      "start": 1508.6,
      "end": 1510.6,
      "speaker": "SPEAKER_03",
      "text": "Por suerte."
    },
    {
      "start": 1510.6,
      "end": 1512.6,
      "speaker": "SPEAKER_03",
      "text": "Con un poco de suerte tendremos una finalísima."
    },
    {
      "start": 1512.6,
      "end": 1514.6,
      "speaker": "SPEAKER_03",
      "text": "Para poder dirimir esta cuestión."
    },
    {
      "start": 1514.6,
      "end": 1516.6,
      "speaker": "SPEAKER_00",
      "text": "A ti te parece tan importante esas dos piezas."
    },
    {
      "start": 1516.6,
      "end": 1518.6,
      "speaker": "SPEAKER_00",
      "text": "Quizás el movimiento lo está haciendo muy bien."
    },
    {
      "start": 1518.6,
      "end": 1520.6,
      "speaker": "SPEAKER_00",
      "text": "Y luego a mí el tema del lateral derecho"
    },
    {
      "start": 1520.9199999999998,
      "end": 1522.9199999999998,
      "speaker": "SPEAKER_00",
      "text": "sí que me genera dudas."
    },
    {
      "start": 1522.9199999999998,
      "end": 1524.9199999999998,
      "speaker": "SPEAKER_03",
      "text": "En Argentina juega Nahuel Molina."
    },
    {
      "start": 1524.9199999999998,
      "end": 1526.9199999999998,
      "speaker": "SPEAKER_03",
      "text": "Y si no juega Molina juega Montiel."
    },
    {
      "start": 1526.9199999999998,
      "end": 1528.9199999999998,
      "speaker": "SPEAKER_03",
      "text": "Entonces, quiero decir..."
    },
    {
      "start": 1528.9199999999998,
      "end": 1530.9199999999998,
      "speaker": "SPEAKER_03",
      "text": "A la hora de hacer la comparativa"
    },
    {
      "start": 1530.9199999999998,
      "end": 1532.9199999999998,
      "speaker": "SPEAKER_03",
      "text": "puede influir."
    },
    {
      "start": 1532.9199999999998,
      "end": 1534.9199999999998,
      "speaker": "SPEAKER_03",
      "text": "Igual que estamos haciendo"
    },
    {
      "start": 1534.9199999999998,
      "end": 1536.9199999999998,
      "speaker": "SPEAKER_03",
      "text": "esta clasificación ahora."
    },
    {
      "start": 1536.9199999999998,
      "end": 1538.9199999999998,
      "speaker": "SPEAKER_03",
      "text": "Y de aquí a 9 meses hay mil lesiones."
    },
    {
      "start": 1538.9199999999998,
      "end": 1540.9199999999998,
      "speaker": "SPEAKER_03",
      "text": "Y va a haber jugadores que van a ir con la lengua afuera."
    },
    {
      "start": 1540.9199999999998,
      "end": 1542.9199999999998,
      "speaker": "SPEAKER_03",
      "text": "Y por eso es tan complicado"
    },
    {
      "start": 1542.9199999999998,
      "end": 1544.9199999999998,
      "speaker": "SPEAKER_03",
      "text": "hacer un pronóstico de equipos que juegan"
    },
    {
      "start": 1544.9199999999998,
      "end": 1546.9199999999998,
      "speaker": "SPEAKER_03",
      "text": "tan poco juntos como es el fútbol de selecciones."
    },
    {
      "start": 1546.9199999999998,
      "end": 1548.9199999999998,
      "speaker": "SPEAKER_03",
      "text": "Y sobre todo con tanto tiempo por delante."
    },
    {
      "start": 1549.24,
      "end": 1551.24,
      "speaker": "SPEAKER_00",
      "text": "Por eso lo vamos a ir actualizando"
    },
    {
      "start": 1551.24,
      "end": 1553.24,
      "speaker": "SPEAKER_00",
      "text": "en cada parón de selecciones."
    },
    {
      "start": 1553.24,
      "end": 1555.24,
      "speaker": "SPEAKER_00",
      "text": "Este es nuestro top 10"
    },
    {
      "start": 1555.24,
      "end": 1557.24,
      "speaker": "SPEAKER_00",
      "text": "en el mes de septiembre"
    },
    {
      "start": 1557.24,
      "end": 1559.24,
      "speaker": "SPEAKER_00",
      "text": "de cara al mundial 2026."
    },
    {
      "start": 1559.24,
      "end": 1561.24,
      "speaker": "SPEAKER_00",
      "text": "Argentina, España,"
    },
    {
      "start": 1561.24,
      "end": 1563.24,
      "speaker": "SPEAKER_00",
      "text": "Portugal, Francia, Inglaterra,"
    },
    {
      "start": 1563.24,
      "end": 1565.24,
      "speaker": "SPEAKER_00",
      "text": "Brasil, Países Bajos, Alemania,"
    },
    {
      "start": 1565.24,
      "end": 1567.24,
      "speaker": "SPEAKER_00",
      "text": "Marruecos y Uruguay."
    },
    {
      "start": 1578.92,
      "end": 1580.92,
      "speaker": "SPEAKER_??",
      "text": "¡Gracias por ver!"
    }
  ]
}